Compiled from "BlockRegistry.java"
public class org.betterx.wover.block.api.BlockRegistry {
  private static final java.util.Map<org.betterx.wover.core.api.ModCore, org.betterx.wover.block.api.BlockRegistry> REGISTRIES;

  private static final java.util.Comparator<org.betterx.wover.block.api.BlockRegistry> REGISTRY_ORDER;

  private static final java.util.Comparator<net.minecraft.resources.Identifier> ID_ORDER;

  private static final java.util.concurrent.atomic.AtomicBoolean HOOKED;

  private static final java.lang.ThreadLocal<java.util.ArrayDeque<net.minecraft.resources.ResourceKey<net.minecraft.world.level.block.Block>>> CONSTRUCTION_IDS;

  public final org.betterx.wover.core.api.ModCore C;

  private final java.util.Map<net.minecraft.resources.Identifier, net.minecraft.world.level.block.Block> blocks;

  private java.util.Map<net.minecraft.world.level.block.Block, net.minecraft.tags.TagKey<net.minecraft.world.level.block.Block>[]> datagenTags;

  private final org.betterx.wover.item.api.ItemRegistry itemRegistry;

  private java.lang.Runnable initializer;

  private boolean initialized;

  private org.betterx.wover.block.api.BlockRegistry(org.betterx.wover.core.api.ModCore);
    Code:
       0: aload_0
       1: invokespecial #1                  // Method java/lang/Object."<init>":()V
       4: aload_0
       5: new           #7                  // class java/util/HashMap
       8: dup
       9: invokespecial #9                  // Method java/util/HashMap."<init>":()V
      12: putfield      #10                 // Field blocks:Ljava/util/Map;
      15: aload_0
      16: aload_1
      17: putfield      #16                 // Field C:Lorg/betterx/wover/core/api/ModCore;
      20: aload_0
      21: aload_1
      22: invokestatic  #20                 // Method org/betterx/wover/item/api/ItemRegistry.forMod:(Lorg/betterx/wover/core/api/ModCore;)Lorg/betterx/wover/item/api/ItemRegistry;
      25: putfield      #26                 // Field itemRegistry:Lorg/betterx/wover/item/api/ItemRegistry;
      28: invokestatic  #30                 // Method org/betterx/wover/core/api/ModCore.isDatagen:()Z
      31: ifeq          45
      34: aload_0
      35: new           #7                  // class java/util/HashMap
      38: dup
      39: invokespecial #9                  // Method java/util/HashMap."<init>":()V
      42: putfield      #36                 // Field datagenTags:Ljava/util/Map;
      45: return

  public static java.util.stream.Stream<org.betterx.wover.block.api.BlockRegistry> streamAll();
    Code:
       0: getstatic     #39                 // Field REGISTRIES:Ljava/util/Map;
       3: invokeinterface #42,  1           // InterfaceMethod java/util/Map.values:()Ljava/util/Collection;
       8: invokeinterface #48,  1           // InterfaceMethod java/util/Collection.stream:()Ljava/util/stream/Stream;
      13: areturn

  public static org.betterx.wover.block.api.BlockRegistry forMod(org.betterx.wover.core.api.ModCore);
    Code:
       0: getstatic     #39                 // Field REGISTRIES:Ljava/util/Map;
       3: aload_0
       4: aload_0
       5: invokedynamic #54,  0             // InvokeDynamic #0:apply:(Lorg/betterx/wover/core/api/ModCore;)Ljava/util/function/Function;
      10: invokeinterface #58,  3           // InterfaceMethod java/util/Map.computeIfAbsent:(Ljava/lang/Object;Ljava/util/function/Function;)Ljava/lang/Object;
      15: checkcast     #11                 // class org/betterx/wover/block/api/BlockRegistry
      18: areturn

  public java.util.stream.Stream<net.minecraft.world.level.block.Block> allBlocks();
    Code:
       0: aload_0
       1: getfield      #10                 // Field blocks:Ljava/util/Map;
       4: invokeinterface #42,  1           // InterfaceMethod java/util/Map.values:()Ljava/util/Collection;
       9: invokeinterface #48,  1           // InterfaceMethod java/util/Collection.stream:()Ljava/util/stream/Stream;
      14: areturn

  public java.util.stream.Stream<net.minecraft.world.item.BlockItem> allBlockItems();
    Code:
       0: aload_0
       1: getfield      #10                 // Field blocks:Ljava/util/Map;
       4: invokeinterface #42,  1           // InterfaceMethod java/util/Map.values:()Ljava/util/Collection;
       9: invokeinterface #48,  1           // InterfaceMethod java/util/Collection.stream:()Ljava/util/stream/Stream;
      14: invokedynamic #62,  0             // InvokeDynamic #1:test:()Ljava/util/function/Predicate;
      19: invokeinterface #66,  2           // InterfaceMethod java/util/stream/Stream.filter:(Ljava/util/function/Predicate;)Ljava/util/stream/Stream;
      24: invokedynamic #72,  0             // InvokeDynamic #2:apply:()Ljava/util/function/Function;
      29: invokeinterface #75,  2           // InterfaceMethod java/util/stream/Stream.map:(Ljava/util/function/Function;)Ljava/util/stream/Stream;
      34: areturn

  public final <T extends net.minecraft.world.level.block.Block> T register(java.lang.String, T, net.minecraft.tags.TagKey<net.minecraft.world.level.block.Block>...);
    Code:
       0: aload_0
       1: aload_1
       2: aload_2
       3: aload_3
       4: aconst_null
       5: invokevirtual #79                 // Method register:(Ljava/lang/String;Lnet/minecraft/world/level/block/Block;[Lnet/minecraft/tags/TagKey;[Lnet/minecraft/tags/TagKey;)Lnet/minecraft/world/level/block/Block;
       8: areturn

  public <T extends net.minecraft.world.level.block.Block> T register(java.lang.String, T, net.minecraft.tags.TagKey<net.minecraft.world.level.block.Block>[], net.minecraft.tags.TagKey<net.minecraft.world.item.Item>[]);
    Code:
       0: aload_2
       1: ifnull        157
       4: aload_2
       5: getstatic     #83                 // Field net/minecraft/world/level/block/Blocks.AIR:Lnet/minecraft/world/level/block/Block;
       8: if_acmpeq     157
      11: aload_2
      12: invokestatic  #89                 // Method ensureIntrusiveHolder:(Lnet/minecraft/world/level/block/Block;)V
      15: aload_3
      16: ifnonnull     32
      19: aload_0
      20: aload_1
      21: aload_2
      22: iconst_0
      23: anewarray     #93                 // class net/minecraft/tags/TagKey
      26: invokevirtual #95                 // Method _registerBlockOnly:(Ljava/lang/String;Lnet/minecraft/world/level/block/Block;[Lnet/minecraft/tags/TagKey;)Lnet/minecraft/resources/Identifier;
      29: goto          39
      32: aload_0
      33: aload_1
      34: aload_2
      35: aload_3
      36: invokevirtual #95                 // Method _registerBlockOnly:(Ljava/lang/String;Lnet/minecraft/world/level/block/Block;[Lnet/minecraft/tags/TagKey;)Lnet/minecraft/resources/Identifier;
      39: astore        5
      41: aload         5
      43: invokestatic  #99                 // Method org/betterx/wover/item/api/ItemRegistry.pushConstructionId:(Lnet/minecraft/resources/Identifier;)V
      46: aload_2
      47: instanceof    #103                // class org/betterx/wover/block/api/CustomBlockItemProvider
      50: ifeq          77
      53: aload_2
      54: checkcast     #103                // class org/betterx/wover/block/api/CustomBlockItemProvider
      57: astore        7
      59: aload         7
      61: aload         5
      63: aload_0
      64: invokevirtual #105                // Method defaultBlockItemSettings:()Lnet/minecraft/world/item/Item$Properties;
      67: invokeinterface #109,  3          // InterfaceMethod org/betterx/wover/block/api/CustomBlockItemProvider.getCustomBlockItem:(Lnet/minecraft/resources/Identifier;Lnet/minecraft/world/item/Item$Properties;)Lnet/minecraft/world/item/BlockItem;
      72: astore        6
      74: goto          87
      77: aload_2
      78: aload_0
      79: invokevirtual #105                // Method defaultBlockItemSettings:()Lnet/minecraft/world/item/Item$Properties;
      82: invokestatic  #113                // Method org/betterx/wover/block/impl/WoverBlockItemImpl.create:(Lnet/minecraft/world/level/block/Block;Lnet/minecraft/world/item/Item$Properties;)Lnet/minecraft/world/item/BlockItem;
      85: astore        6
      87: invokestatic  #119                // Method org/betterx/wover/item/api/ItemRegistry.popConstructionId:()V
      90: goto          101
      93: astore        8
      95: invokestatic  #119                // Method org/betterx/wover/item/api/ItemRegistry.popConstructionId:()V
      98: aload         8
     100: athrow
     101: aload         4
     103: ifnonnull     121
     106: aload_0
     107: aload_1
     108: aload         6
     110: iconst_0
     111: anewarray     #93                 // class net/minecraft/tags/TagKey
     114: invokevirtual #122                // Method registerBlockItem:(Ljava/lang/String;Lnet/minecraft/world/item/BlockItem;[Lnet/minecraft/tags/TagKey;)Lnet/minecraft/world/item/BlockItem;
     117: pop
     118: goto          131
     121: aload_0
     122: aload_1
     123: aload         6
     125: aload         4
     127: invokevirtual #122                // Method registerBlockItem:(Ljava/lang/String;Lnet/minecraft/world/item/BlockItem;[Lnet/minecraft/tags/TagKey;)Lnet/minecraft/world/item/BlockItem;
     130: pop
     131: aload_2
     132: invokevirtual #126                // Method net/minecraft/world/level/block/Block.defaultBlockState:()Lnet/minecraft/world/level/block/state/BlockState;
     135: invokevirtual #132                // Method net/minecraft/world/level/block/state/BlockState.ignitedByLava:()Z
     138: ifeq          157
     141: getstatic     #137                // Field net/minecraft/world/level/block/Blocks.FIRE:Lnet/minecraft/world/level/block/Block;
     144: checkcast     #140                // class net/minecraft/world/level/block/FireBlock
     147: astore        7
     149: aload         7
     151: aload_2
     152: iconst_5
     153: iconst_5
     154: invokevirtual #142                // Method net/minecraft/world/level/block/FireBlock.setFlammable:(Lnet/minecraft/world/level/block/Block;II)V
     157: aload_2
     158: areturn
    Exception table:
       from    to  target type
          46    87    93   any
          93    95    93   any

  private net.minecraft.resources.Identifier _registerBlockOnly(java.lang.String, net.minecraft.world.level.block.Block, net.minecraft.tags.TagKey<net.minecraft.world.level.block.Block>...);
    Code:
       0: aload_0
       1: getfield      #16                 // Field C:Lorg/betterx/wover/core/api/ModCore;
       4: aload_1
       5: invokevirtual #146                // Method org/betterx/wover/core/api/ModCore.mk:(Ljava/lang/String;)Lnet/minecraft/resources/Identifier;
       8: astore        4
      10: aload_0
      11: getfield      #10                 // Field blocks:Ljava/util/Map;
      14: aload         4
      16: aload_2
      17: invokeinterface #150,  3          // InterfaceMethod java/util/Map.put:(Ljava/lang/Object;Ljava/lang/Object;)Ljava/lang/Object;
      22: pop
      23: aload_0
      24: getfield      #36                 // Field datagenTags:Ljava/util/Map;
      27: ifnull        51
      30: aload_3
      31: ifnull        51
      34: aload_3
      35: arraylength
      36: ifle          51
      39: aload_0
      40: getfield      #36                 // Field datagenTags:Ljava/util/Map;
      43: aload_2
      44: aload_3
      45: invokeinterface #150,  3          // InterfaceMethod java/util/Map.put:(Ljava/lang/Object;Ljava/lang/Object;)Ljava/lang/Object;
      50: pop
      51: aload         4
      53: areturn

  public final <T extends net.minecraft.world.level.block.Block> T registerBlockOnly(java.lang.String, T, net.minecraft.tags.TagKey<net.minecraft.world.level.block.Block>...);
    Code:
       0: aload_2
       1: ifnull        23
       4: aload_2
       5: getstatic     #83                 // Field net/minecraft/world/level/block/Blocks.AIR:Lnet/minecraft/world/level/block/Block;
       8: if_acmpeq     23
      11: aload_2
      12: invokestatic  #89                 // Method ensureIntrusiveHolder:(Lnet/minecraft/world/level/block/Block;)V
      15: aload_0
      16: aload_1
      17: aload_2
      18: aload_3
      19: invokevirtual #95                 // Method _registerBlockOnly:(Ljava/lang/String;Lnet/minecraft/world/level/block/Block;[Lnet/minecraft/tags/TagKey;)Lnet/minecraft/resources/Identifier;
      22: pop
      23: aload_2
      24: areturn

  private net.minecraft.world.item.BlockItem registerBlockItem(java.lang.String, net.minecraft.world.item.BlockItem, net.minecraft.tags.TagKey<net.minecraft.world.item.Item>...);
    Code:
       0: aload_0
       1: getfield      #26                 // Field itemRegistry:Lorg/betterx/wover/item/api/ItemRegistry;
       4: aload_1
       5: aload_2
       6: aload_3
       7: invokevirtual #154                // Method org/betterx/wover/item/api/ItemRegistry.register:(Ljava/lang/String;Lnet/minecraft/world/item/Item;[Lnet/minecraft/tags/TagKey;)Lnet/minecraft/world/item/Item;
      10: pop
      11: aload_2
      12: areturn

  public void setInitializer(java.lang.Runnable);
    Code:
       0: aload_0
       1: aload_1
       2: putfield      #157                // Field initializer:Ljava/lang/Runnable;
       5: return

  public java.lang.String prepareConstructionPath(java.lang.String);
    Code:
       0: aload_0
       1: getfield      #16                 // Field C:Lorg/betterx/wover/core/api/ModCore;
       4: aload_1
       5: invokevirtual #146                // Method org/betterx/wover/core/api/ModCore.mk:(Ljava/lang/String;)Lnet/minecraft/resources/Identifier;
       8: invokestatic  #161                // Method pushConstructionId:(Lnet/minecraft/resources/Identifier;)V
      11: aload_1
      12: areturn

  public void finishConstructionPath();
    Code:
       0: invokestatic  #162                // Method popConstructionId:()V
       3: return

  private void ensureInitialized();
    Code:
       0: aload_0
       1: getfield      #163                // Field initialized:Z
       4: ifne          28
       7: aload_0
       8: getfield      #157                // Field initializer:Ljava/lang/Runnable;
      11: ifnull        28
      14: aload_0
      15: iconst_1
      16: putfield      #163                // Field initialized:Z
      19: aload_0
      20: getfield      #157                // Field initializer:Ljava/lang/Runnable;
      23: invokeinterface #167,  1          // InterfaceMethod java/lang/Runnable.run:()V
      28: return

  protected net.minecraft.world.item.Item$Properties defaultBlockItemSettings();
    Code:
       0: new           #172                // class net/minecraft/world/item/Item$Properties
       3: dup
       4: invokespecial #174                // Method net/minecraft/world/item/Item$Properties."<init>":()V
       7: invokevirtual #175                // Method net/minecraft/world/item/Item$Properties.useBlockDescriptionPrefix:()Lnet/minecraft/world/item/Item$Properties;
      10: areturn

  public void bootstrapBlockTags(org.betterx.wover.tag.api.event.context.TagBootstrapContext<net.minecraft.world.level.block.Block>);
    Code:
       0: aload_0
       1: getfield      #36                 // Field datagenTags:Ljava/util/Map;
       4: ifnull        27
       7: aload_0
       8: getfield      #36                 // Field datagenTags:Ljava/util/Map;
      11: aload_1
      12: dup
      13: invokestatic  #178                // Method java/util/Objects.requireNonNull:(Ljava/lang/Object;)Ljava/lang/Object;
      16: pop
      17: invokedynamic #184,  0            // InvokeDynamic #3:accept:(Lorg/betterx/wover/tag/api/event/context/TagBootstrapContext;)Ljava/util/function/BiConsumer;
      22: invokeinterface #188,  2          // InterfaceMethod java/util/Map.forEach:(Ljava/util/function/BiConsumer;)V
      27: aload_0
      28: getfield      #10                 // Field blocks:Ljava/util/Map;
      31: invokeinterface #192,  1          // InterfaceMethod java/util/Map.entrySet:()Ljava/util/Set;
      36: invokeinterface #196,  1          // InterfaceMethod java/util/Set.stream:()Ljava/util/stream/Stream;
      41: invokedynamic #199,  0            // InvokeDynamic #4:test:()Ljava/util/function/Predicate;
      46: invokeinterface #66,  2           // InterfaceMethod java/util/stream/Stream.filter:(Ljava/util/function/Predicate;)Ljava/util/stream/Stream;
      51: aload_1
      52: invokedynamic #200,  0            // InvokeDynamic #5:accept:(Lorg/betterx/wover/tag/api/event/context/TagBootstrapContext;)Ljava/util/function/Consumer;
      57: invokeinterface #203,  2          // InterfaceMethod java/util/stream/Stream.forEach:(Ljava/util/function/Consumer;)V
      62: return

  public void bootstrapBlockLoot(net.minecraft.core.HolderLookup$Provider, java.util.function.BiConsumer<net.minecraft.resources.ResourceKey<net.minecraft.world.level.storage.loot.LootTable>, net.minecraft.world.level.storage.loot.LootTable$Builder>);
    Code:
       0: new           #206                // class org/betterx/wover/loot/api/LootLookupProvider
       3: dup
       4: aload_1
       5: invokespecial #208                // Method org/betterx/wover/loot/api/LootLookupProvider."<init>":(Lnet/minecraft/core/HolderLookup$Provider;)V
       8: astore_3
       9: aload_0
      10: getfield      #10                 // Field blocks:Ljava/util/Map;
      13: invokeinterface #192,  1          // InterfaceMethod java/util/Map.entrySet:()Ljava/util/Set;
      18: invokeinterface #196,  1          // InterfaceMethod java/util/Set.stream:()Ljava/util/stream/Stream;
      23: invokedynamic #211,  0            // InvokeDynamic #6:test:()Ljava/util/function/Predicate;
      28: invokeinterface #66,  2           // InterfaceMethod java/util/stream/Stream.filter:(Ljava/util/function/Predicate;)Ljava/util/stream/Stream;
      33: aload_0
      34: aload_3
      35: aload_2
      36: invokedynamic #212,  0            // InvokeDynamic #7:accept:(Lorg/betterx/wover/block/api/BlockRegistry;Lorg/betterx/wover/loot/api/LootLookupProvider;Ljava/util/function/BiConsumer;)Ljava/util/function/Consumer;
      41: invokeinterface #203,  2          // InterfaceMethod java/util/stream/Stream.forEach:(Ljava/util/function/Consumer;)V
      46: return

  private void performBlockRegistration(net.neoforged.neoforge.registries.RegisterEvent$RegisterHelper<net.minecraft.world.level.block.Block>);
    Code:
       0: aload_0
       1: invokevirtual #215                // Method ensureInitialized:()V
       4: aload_0
       5: getfield      #10                 // Field blocks:Ljava/util/Map;
       8: invokeinterface #192,  1          // InterfaceMethod java/util/Map.entrySet:()Ljava/util/Set;
      13: invokeinterface #196,  1          // InterfaceMethod java/util/Set.stream:()Ljava/util/stream/Stream;
      18: getstatic     #218                // Field ID_ORDER:Ljava/util/Comparator;
      21: invokestatic  #222                // InterfaceMethod java/util/Map$Entry.comparingByKey:(Ljava/util/Comparator;)Ljava/util/Comparator;
      24: invokeinterface #228,  2          // InterfaceMethod java/util/stream/Stream.sorted:(Ljava/util/Comparator;)Ljava/util/stream/Stream;
      29: aload_1
      30: invokedynamic #232,  0            // InvokeDynamic #8:accept:(Lnet/neoforged/neoforge/registries/RegisterEvent$RegisterHelper;)Ljava/util/function/Consumer;
      35: invokeinterface #203,  2          // InterfaceMethod java/util/stream/Stream.forEach:(Ljava/util/function/Consumer;)V
      40: return

  private static void ensureIntrusiveHolder(net.minecraft.world.level.block.Block);
    Code:
       0: getstatic     #235                // Field net/minecraft/core/registries/BuiltInRegistries.BLOCK:Lnet/minecraft/core/DefaultedRegistry;
       3: aload_0
       4: invokeinterface #241,  2          // InterfaceMethod net/minecraft/core/DefaultedRegistry.createIntrusiveHolder:(Ljava/lang/Object;)Lnet/minecraft/core/Holder$Reference;
       9: pop
      10: return

  public static void onRegister(net.neoforged.neoforge.registries.RegisterEvent);
    Code:
       0: aload_0
       1: invokevirtual #247                // Method net/neoforged/neoforge/registries/RegisterEvent.getRegistryKey:()Lnet/minecraft/resources/ResourceKey;
       4: getstatic     #253                // Field net/minecraft/core/registries/Registries.BLOCK:Lnet/minecraft/resources/ResourceKey;
       7: invokevirtual #258                // Method java/lang/Object.equals:(Ljava/lang/Object;)Z
      10: ifeq          25
      13: aload_0
      14: getstatic     #253                // Field net/minecraft/core/registries/Registries.BLOCK:Lnet/minecraft/resources/ResourceKey;
      17: invokedynamic #262,  0            // InvokeDynamic #9:accept:()Ljava/util/function/Consumer;
      22: invokevirtual #265                // Method net/neoforged/neoforge/registries/RegisterEvent.register:(Lnet/minecraft/resources/ResourceKey;Ljava/util/function/Consumer;)V
      25: return

  public static void hook(net.neoforged.bus.api.IEventBus);
    Code:
       0: getstatic     #268                // Field HOOKED:Ljava/util/concurrent/atomic/AtomicBoolean;
       3: iconst_0
       4: iconst_1
       5: invokevirtual #272                // Method java/util/concurrent/atomic/AtomicBoolean.compareAndSet:(ZZ)Z
       8: ifeq          24
      11: aload_0
      12: ldc           #248                // class net/neoforged/neoforge/registries/RegisterEvent
      14: invokedynamic #278,  0            // InvokeDynamic #10:accept:()Ljava/util/function/Consumer;
      19: invokeinterface #279,  3          // InterfaceMethod net/neoforged/bus/api/IEventBus.addListener:(Ljava/lang/Class;Ljava/util/function/Consumer;)V
      24: return

  private static void pushConstructionId(net.minecraft.resources.Identifier);
    Code:
       0: getstatic     #285                // Field CONSTRUCTION_IDS:Ljava/lang/ThreadLocal;
       3: invokevirtual #289                // Method java/lang/ThreadLocal.get:()Ljava/lang/Object;
       6: checkcast     #295                // class java/util/ArrayDeque
       9: getstatic     #253                // Field net/minecraft/core/registries/Registries.BLOCK:Lnet/minecraft/resources/ResourceKey;
      12: aload_0
      13: invokestatic  #297                // Method net/minecraft/resources/ResourceKey.create:(Lnet/minecraft/resources/ResourceKey;Lnet/minecraft/resources/Identifier;)Lnet/minecraft/resources/ResourceKey;
      16: invokevirtual #302                // Method java/util/ArrayDeque.push:(Ljava/lang/Object;)V
      19: return

  private static void popConstructionId();
    Code:
       0: getstatic     #285                // Field CONSTRUCTION_IDS:Ljava/lang/ThreadLocal;
       3: invokevirtual #289                // Method java/lang/ThreadLocal.get:()Ljava/lang/Object;
       6: checkcast     #295                // class java/util/ArrayDeque
       9: astore_0
      10: aload_0
      11: invokevirtual #306                // Method java/util/ArrayDeque.isEmpty:()Z
      14: ifne          22
      17: aload_0
      18: invokevirtual #309                // Method java/util/ArrayDeque.pop:()Ljava/lang/Object;
      21: pop
      22: return

  public static net.minecraft.resources.ResourceKey<net.minecraft.world.level.block.Block> peekConstructionId();
    Code:
       0: getstatic     #285                // Field CONSTRUCTION_IDS:Ljava/lang/ThreadLocal;
       3: invokevirtual #289                // Method java/lang/ThreadLocal.get:()Ljava/lang/Object;
       6: checkcast     #295                // class java/util/ArrayDeque
       9: invokevirtual #312                // Method java/util/ArrayDeque.peek:()Ljava/lang/Object;
      12: checkcast     #298                // class net/minecraft/resources/ResourceKey
      15: areturn

  public static net.minecraft.resources.ResourceKey<net.minecraft.world.level.block.Block> takeConstructionId();
    Code:
       0: getstatic     #285                // Field CONSTRUCTION_IDS:Ljava/lang/ThreadLocal;
       3: invokevirtual #289                // Method java/lang/ThreadLocal.get:()Ljava/lang/Object;
       6: checkcast     #295                // class java/util/ArrayDeque
       9: astore_0
      10: aload_0
      11: invokevirtual #306                // Method java/util/ArrayDeque.isEmpty:()Z
      14: ifeq          21
      17: aconst_null
      18: goto          28
      21: aload_0
      22: invokevirtual #309                // Method java/util/ArrayDeque.pop:()Ljava/lang/Object;
      25: checkcast     #298                // class net/minecraft/resources/ResourceKey
      28: areturn

  public static java.lang.String takeConstructionIdString();
    Code:
       0: invokestatic  #315                // Method takeConstructionId:()Lnet/minecraft/resources/ResourceKey;
       3: astore_0
       4: aload_0
       5: ifnonnull     12
       8: aconst_null
       9: goto          19
      12: aload_0
      13: invokevirtual #318                // Method net/minecraft/resources/ResourceKey.identifier:()Lnet/minecraft/resources/Identifier;
      16: invokevirtual #322                // Method net/minecraft/resources/Identifier.toString:()Ljava/lang/String;
      19: areturn

  public static <T> T withConstructionId(net.minecraft.resources.Identifier, java.util.function.Supplier<T>);
    Code:
       0: getstatic     #253                // Field net/minecraft/core/registries/Registries.BLOCK:Lnet/minecraft/resources/ResourceKey;
       3: aload_0
       4: invokestatic  #297                // Method net/minecraft/resources/ResourceKey.create:(Lnet/minecraft/resources/ResourceKey;Lnet/minecraft/resources/Identifier;)Lnet/minecraft/resources/ResourceKey;
       7: astore_2
       8: getstatic     #285                // Field CONSTRUCTION_IDS:Ljava/lang/ThreadLocal;
      11: invokevirtual #289                // Method java/lang/ThreadLocal.get:()Ljava/lang/Object;
      14: checkcast     #295                // class java/util/ArrayDeque
      17: astore_3
      18: aload_3
      19: aload_2
      20: invokevirtual #302                // Method java/util/ArrayDeque.push:(Ljava/lang/Object;)V
      23: aload_1
      24: invokeinterface #328,  1          // InterfaceMethod java/util/function/Supplier.get:()Ljava/lang/Object;
      29: astore        4
      31: aload_3
      32: invokevirtual #306                // Method java/util/ArrayDeque.isEmpty:()Z
      35: ifne          54
      38: aload_2
      39: aload_3
      40: invokevirtual #312                // Method java/util/ArrayDeque.peek:()Ljava/lang/Object;
      43: invokevirtual #258                // Method java/lang/Object.equals:(Ljava/lang/Object;)Z
      46: ifeq          54
      49: aload_3
      50: invokevirtual #309                // Method java/util/ArrayDeque.pop:()Ljava/lang/Object;
      53: pop
      54: aload         4
      56: areturn
      57: astore        5
      59: aload_3
      60: invokevirtual #306                // Method java/util/ArrayDeque.isEmpty:()Z
      63: ifne          82
      66: aload_2
      67: aload_3
      68: invokevirtual #312                // Method java/util/ArrayDeque.peek:()Ljava/lang/Object;
      71: invokevirtual #258                // Method java/lang/Object.equals:(Ljava/lang/Object;)Z
      74: ifeq          82
      77: aload_3
      78: invokevirtual #309                // Method java/util/ArrayDeque.pop:()Ljava/lang/Object;
      81: pop
      82: aload         5
      84: athrow
    Exception table:
       from    to  target type
          23    31    57   any
          57    59    57   any

  private static void lambda$onRegister$12(net.neoforged.neoforge.registries.RegisterEvent$RegisterHelper);
    Code:
       0: getstatic     #39                 // Field REGISTRIES:Ljava/util/Map;
       3: invokeinterface #42,  1           // InterfaceMethod java/util/Map.values:()Ljava/util/Collection;
       8: invokeinterface #48,  1           // InterfaceMethod java/util/Collection.stream:()Ljava/util/stream/Stream;
      13: getstatic     #331                // Field REGISTRY_ORDER:Ljava/util/Comparator;
      16: invokeinterface #228,  2          // InterfaceMethod java/util/stream/Stream.sorted:(Ljava/util/Comparator;)Ljava/util/stream/Stream;
      21: aload_0
      22: invokedynamic #334,  0            // InvokeDynamic #11:accept:(Lnet/neoforged/neoforge/registries/RegisterEvent$RegisterHelper;)Ljava/util/function/Consumer;
      27: invokeinterface #203,  2          // InterfaceMethod java/util/stream/Stream.forEach:(Ljava/util/function/Consumer;)V
      32: return

  private static void lambda$onRegister$11(net.neoforged.neoforge.registries.RegisterEvent$RegisterHelper, org.betterx.wover.block.api.BlockRegistry);
    Code:
       0: aload_1
       1: aload_0
       2: invokevirtual #335                // Method performBlockRegistration:(Lnet/neoforged/neoforge/registries/RegisterEvent$RegisterHelper;)V
       5: return

  private static void lambda$performBlockRegistration$10(net.neoforged.neoforge.registries.RegisterEvent$RegisterHelper, java.util.Map$Entry);
    Code:
       0: aload_1
       1: invokeinterface #339,  1          // InterfaceMethod java/util/Map$Entry.getKey:()Ljava/lang/Object;
       6: checkcast     #323                // class net/minecraft/resources/Identifier
       9: astore_2
      10: aload_1
      11: invokeinterface #342,  1          // InterfaceMethod java/util/Map$Entry.getValue:()Ljava/lang/Object;
      16: checkcast     #127                // class net/minecraft/world/level/block/Block
      19: astore_3
      20: aload_3
      21: invokestatic  #89                 // Method ensureIntrusiveHolder:(Lnet/minecraft/world/level/block/Block;)V
      24: aload_0
      25: aload_2
      26: aload_3
      27: invokeinterface #345,  3          // InterfaceMethod net/neoforged/neoforge/registries/RegisterEvent$RegisterHelper.register:(Lnet/minecraft/resources/Identifier;Ljava/lang/Object;)V
      32: getstatic     #253                // Field net/minecraft/core/registries/Registries.BLOCK:Lnet/minecraft/resources/ResourceKey;
      35: aload_2
      36: invokestatic  #297                // Method net/minecraft/resources/ResourceKey.create:(Lnet/minecraft/resources/ResourceKey;Lnet/minecraft/resources/Identifier;)Lnet/minecraft/resources/ResourceKey;
      39: astore        4
      41: getstatic     #235                // Field net/minecraft/core/registries/BuiltInRegistries.BLOCK:Lnet/minecraft/core/DefaultedRegistry;
      44: aload         4
      46: invokeinterface #350,  2          // InterfaceMethod net/minecraft/core/DefaultedRegistry.get:(Lnet/minecraft/resources/ResourceKey;)Ljava/util/Optional;
      51: aload_3
      52: invokedynamic #353,  0            // InvokeDynamic #12:accept:(Lnet/minecraft/world/level/block/Block;)Ljava/util/function/Consumer;
      57: invokevirtual #356                // Method java/util/Optional.ifPresent:(Ljava/util/function/Consumer;)V
      60: return

  private static void lambda$performBlockRegistration$9(net.minecraft.world.level.block.Block, net.minecraft.core.Holder$Reference);
    Code:
       0: aload_0
       1: checkcast     #361                // class org/betterx/wover/block/impl/BlockHolderBridge
       4: aload_1
       5: invokeinterface #363,  2          // InterfaceMethod org/betterx/wover/block/impl/BlockHolderBridge.wover$setBuiltInRegistryHolder:(Lnet/minecraft/core/Holder$Reference;)V
      10: return

  private void lambda$bootstrapBlockLoot$8(org.betterx.wover.loot.api.LootLookupProvider, java.util.function.BiConsumer, java.util.Map$Entry);
    Code:
       0: aload_0
       1: getfield      #16                 // Field C:Lorg/betterx/wover/core/api/ModCore;
       4: aload_3
       5: invokeinterface #339,  1          // InterfaceMethod java/util/Map$Entry.getKey:()Ljava/lang/Object;
      10: checkcast     #323                // class net/minecraft/resources/Identifier
      13: invokestatic  #367                // Method org/betterx/wover/loot/api/LootTableManager.getBlockLootTableKey:(Lorg/betterx/wover/core/api/ModCore;Lnet/minecraft/resources/Identifier;)Lnet/minecraft/resources/ResourceKey;
      16: astore        4
      18: aload_3
      19: invokeinterface #342,  1          // InterfaceMethod java/util/Map$Entry.getValue:()Ljava/lang/Object;
      24: checkcast     #373                // class org/betterx/wover/loot/api/BlockLootProvider
      27: aload_3
      28: invokeinterface #339,  1          // InterfaceMethod java/util/Map$Entry.getKey:()Ljava/lang/Object;
      33: checkcast     #323                // class net/minecraft/resources/Identifier
      36: aload_1
      37: aload         4
      39: invokeinterface #375,  4          // InterfaceMethod org/betterx/wover/loot/api/BlockLootProvider.registerBlockLoot:(Lnet/minecraft/resources/Identifier;Lorg/betterx/wover/loot/api/LootLookupProvider;Lnet/minecraft/resources/ResourceKey;)Lnet/minecraft/world/level/storage/loot/LootTable$Builder;
      44: astore        5
      46: aload         5
      48: ifnull        61
      51: aload_2
      52: aload         4
      54: aload         5
      56: invokeinterface #379,  3          // InterfaceMethod java/util/function/BiConsumer.accept:(Ljava/lang/Object;Ljava/lang/Object;)V
      61: return

  private static boolean lambda$bootstrapBlockLoot$7(java.util.Map$Entry);
    Code:
       0: aload_0
       1: invokeinterface #342,  1          // InterfaceMethod java/util/Map$Entry.getValue:()Ljava/lang/Object;
       6: instanceof    #373                // class org/betterx/wover/loot/api/BlockLootProvider
       9: ireturn

  private static void lambda$bootstrapBlockTags$6(org.betterx.wover.tag.api.event.context.TagBootstrapContext, java.util.Map$Entry);
    Code:
       0: aload_1
       1: invokeinterface #342,  1          // InterfaceMethod java/util/Map$Entry.getValue:()Ljava/lang/Object;
       6: checkcast     #384                // class org/betterx/wover/block/api/BlockTagProvider
       9: aload_1
      10: invokeinterface #339,  1          // InterfaceMethod java/util/Map$Entry.getKey:()Ljava/lang/Object;
      15: checkcast     #323                // class net/minecraft/resources/Identifier
      18: aload_0
      19: invokeinterface #386,  3          // InterfaceMethod org/betterx/wover/block/api/BlockTagProvider.registerBlockTags:(Lnet/minecraft/resources/Identifier;Lorg/betterx/wover/tag/api/event/context/TagBootstrapContext;)V
      24: return

  private static boolean lambda$bootstrapBlockTags$5(java.util.Map$Entry);
    Code:
       0: aload_0
       1: invokeinterface #342,  1          // InterfaceMethod java/util/Map$Entry.getValue:()Ljava/lang/Object;
       6: instanceof    #384                // class org/betterx/wover/block/api/BlockTagProvider
       9: ireturn

  private static net.minecraft.world.item.BlockItem lambda$allBlockItems$4(net.minecraft.world.level.block.Block);
    Code:
       0: aload_0
       1: invokevirtual #390                // Method net/minecraft/world/level/block/Block.asItem:()Lnet/minecraft/world/item/Item;
       4: checkcast     #394                // class net/minecraft/world/item/BlockItem
       7: areturn

  private static boolean lambda$allBlockItems$3(net.minecraft.world.level.block.Block);
    Code:
       0: aload_0
       1: invokevirtual #390                // Method net/minecraft/world/level/block/Block.asItem:()Lnet/minecraft/world/item/Item;
       4: instanceof    #394                // class net/minecraft/world/item/BlockItem
       7: ireturn

  private static org.betterx.wover.block.api.BlockRegistry lambda$forMod$2(org.betterx.wover.core.api.ModCore, org.betterx.wover.core.api.ModCore);
    Code:
       0: new           #11                 // class org/betterx/wover/block/api/BlockRegistry
       3: dup
       4: aload_0
       5: invokespecial #396                // Method "<init>":(Lorg/betterx/wover/core/api/ModCore;)V
       8: areturn

  private static java.lang.String lambda$static$1(org.betterx.wover.block.api.BlockRegistry);
    Code:
       0: aload_0
       1: getfield      #16                 // Field C:Lorg/betterx/wover/core/api/ModCore;
       4: getfield      #399                // Field org/betterx/wover/core/api/ModCore.namespace:Ljava/lang/String;
       7: areturn

  private static java.lang.String lambda$static$0(org.betterx.wover.block.api.BlockRegistry);
    Code:
       0: aload_0
       1: getfield      #16                 // Field C:Lorg/betterx/wover/core/api/ModCore;
       4: getfield      #403                // Field org/betterx/wover/core/api/ModCore.modId:Ljava/lang/String;
       7: areturn

  static {};
    Code:
       0: new           #7                  // class java/util/HashMap
       3: dup
       4: invokespecial #9                  // Method java/util/HashMap."<init>":()V
       7: putstatic     #39                 // Field REGISTRIES:Ljava/util/Map;
      10: invokedynamic #406,  0            // InvokeDynamic #13:apply:()Ljava/util/function/Function;
      15: invokestatic  #407                // InterfaceMethod java/util/Comparator.comparing:(Ljava/util/function/Function;)Ljava/util/Comparator;
      18: invokedynamic #413,  0            // InvokeDynamic #14:apply:()Ljava/util/function/Function;
      23: invokeinterface #414,  2          // InterfaceMethod java/util/Comparator.thenComparing:(Ljava/util/function/Function;)Ljava/util/Comparator;
      28: putstatic     #331                // Field REGISTRY_ORDER:Ljava/util/Comparator;
      31: invokedynamic #417,  0            // InvokeDynamic #15:apply:()Ljava/util/function/Function;
      36: invokestatic  #407                // InterfaceMethod java/util/Comparator.comparing:(Ljava/util/function/Function;)Ljava/util/Comparator;
      39: invokedynamic #418,  0            // InvokeDynamic #16:apply:()Ljava/util/function/Function;
      44: invokeinterface #414,  2          // InterfaceMethod java/util/Comparator.thenComparing:(Ljava/util/function/Function;)Ljava/util/Comparator;
      49: putstatic     #218                // Field ID_ORDER:Ljava/util/Comparator;
      52: new           #273                // class java/util/concurrent/atomic/AtomicBoolean
      55: dup
      56: iconst_0
      57: invokespecial #419                // Method java/util/concurrent/atomic/AtomicBoolean."<init>":(Z)V
      60: putstatic     #268                // Field HOOKED:Ljava/util/concurrent/atomic/AtomicBoolean;
      63: invokedynamic #422,  0            // InvokeDynamic #17:get:()Ljava/util/function/Supplier;
      68: invokestatic  #425                // Method java/lang/ThreadLocal.withInitial:(Ljava/util/function/Supplier;)Ljava/lang/ThreadLocal;
      71: putstatic     #285                // Field CONSTRUCTION_IDS:Ljava/lang/ThreadLocal;
      74: return
}

