Compiled from "LevelRenderer.java"
public class net.minecraft.client.renderer.LevelRenderer implements net.minecraft.server.packs.resources.ResourceManagerReloadListener,java.lang.AutoCloseable {
  public static final int SECTION_SIZE;

  public static final int HALF_SECTION_SIZE;

  public static final int NEARBY_SECTION_DISTANCE_IN_BLOCKS;

  public final net.minecraft.client.renderer.debug.DebugRenderer debugRenderer;

  public final net.minecraft.client.renderer.debug.GameTestBlockHighlightRenderer gameTestBlockHighlightRenderer;

  final net.minecraft.client.renderer.state.LevelRenderState levelRenderState;

  public net.minecraft.client.renderer.LevelRenderer(net.minecraft.client.Minecraft, net.minecraft.client.renderer.entity.EntityRenderDispatcher, net.minecraft.client.renderer.blockentity.BlockEntityRenderDispatcher, net.minecraft.client.renderer.RenderBuffers, net.minecraft.client.renderer.state.LevelRenderState, net.minecraft.client.renderer.feature.FeatureRenderDispatcher);
    Code:
       0: aload_0
       1: invokespecial #1                  // Method java/lang/Object."<init>":()V
       4: aload_0
       5: new           #7                  // class net/minecraft/client/renderer/CloudRenderer
       8: dup
       9: invokespecial #9                  // Method net/minecraft/client/renderer/CloudRenderer."<init>":()V
      12: putfield      #10                 // Field cloudRenderer:Lnet/minecraft/client/renderer/CloudRenderer;
      15: aload_0
      16: new           #16                 // class net/minecraft/client/renderer/WorldBorderRenderer
      19: dup
      20: invokespecial #18                 // Method net/minecraft/client/renderer/WorldBorderRenderer."<init>":()V
      23: putfield      #19                 // Field worldBorderRenderer:Lnet/minecraft/client/renderer/WorldBorderRenderer;
      26: aload_0
      27: new           #23                 // class net/minecraft/client/renderer/WeatherEffectRenderer
      30: dup
      31: invokespecial #25                 // Method net/minecraft/client/renderer/WeatherEffectRenderer."<init>":()V
      34: putfield      #26                 // Field weatherEffectRenderer:Lnet/minecraft/client/renderer/WeatherEffectRenderer;
      37: aload_0
      38: new           #30                 // class net/minecraft/client/renderer/state/ParticlesRenderState
      41: dup
      42: invokespecial #32                 // Method net/minecraft/client/renderer/state/ParticlesRenderState."<init>":()V
      45: putfield      #33                 // Field particlesRenderState:Lnet/minecraft/client/renderer/state/ParticlesRenderState;
      48: aload_0
      49: new           #37                 // class net/minecraft/client/renderer/debug/DebugRenderer
      52: dup
      53: invokespecial #39                 // Method net/minecraft/client/renderer/debug/DebugRenderer."<init>":()V
      56: putfield      #40                 // Field debugRenderer:Lnet/minecraft/client/renderer/debug/DebugRenderer;
      59: aload_0
      60: new           #44                 // class net/minecraft/client/renderer/debug/GameTestBlockHighlightRenderer
      63: dup
      64: invokespecial #46                 // Method net/minecraft/client/renderer/debug/GameTestBlockHighlightRenderer."<init>":()V
      67: putfield      #47                 // Field gameTestBlockHighlightRenderer:Lnet/minecraft/client/renderer/debug/GameTestBlockHighlightRenderer;
      70: aload_0
      71: new           #51                 // class net/minecraft/client/renderer/SectionOcclusionGraph
      74: dup
      75: invokespecial #53                 // Method net/minecraft/client/renderer/SectionOcclusionGraph."<init>":()V
      78: putfield      #54                 // Field sectionOcclusionGraph:Lnet/minecraft/client/renderer/SectionOcclusionGraph;
      81: aload_0
      82: new           #58                 // class it/unimi/dsi/fastutil/objects/ObjectArrayList
      85: dup
      86: sipush        10000
      89: invokespecial #60                 // Method it/unimi/dsi/fastutil/objects/ObjectArrayList."<init>":(I)V
      92: putfield      #63                 // Field visibleSections:Lit/unimi/dsi/fastutil/objects/ObjectArrayList;
      95: aload_0
      96: new           #58                 // class it/unimi/dsi/fastutil/objects/ObjectArrayList
      99: dup
     100: bipush        50
     102: invokespecial #60                 // Method it/unimi/dsi/fastutil/objects/ObjectArrayList."<init>":(I)V
     105: putfield      #67                 // Field nearbyVisibleSections:Lit/unimi/dsi/fastutil/objects/ObjectArrayList;
     108: aload_0
     109: new           #70                 // class it/unimi/dsi/fastutil/ints/Int2ObjectOpenHashMap
     112: dup
     113: invokespecial #72                 // Method it/unimi/dsi/fastutil/ints/Int2ObjectOpenHashMap."<init>":()V
     116: putfield      #73                 // Field destroyingBlocks:Lit/unimi/dsi/fastutil/ints/Int2ObjectMap;
     119: aload_0
     120: new           #77                 // class it/unimi/dsi/fastutil/longs/Long2ObjectOpenHashMap
     123: dup
     124: invokespecial #79                 // Method it/unimi/dsi/fastutil/longs/Long2ObjectOpenHashMap."<init>":()V
     127: putfield      #80                 // Field destructionProgress:Lit/unimi/dsi/fastutil/longs/Long2ObjectMap;
     130: aload_0
     131: new           #84                 // class net/minecraft/client/renderer/LevelTargetBundle
     134: dup
     135: invokespecial #86                 // Method net/minecraft/client/renderer/LevelTargetBundle."<init>":()V
     138: putfield      #87                 // Field targets:Lnet/minecraft/client/renderer/LevelTargetBundle;
     141: aload_0
     142: ldc           #93                 // int -2147483648
     144: putfield      #94                 // Field lastCameraSectionX:I
     147: aload_0
     148: ldc           #93                 // int -2147483648
     150: putfield      #98                 // Field lastCameraSectionY:I
     153: aload_0
     154: ldc           #93                 // int -2147483648
     156: putfield      #101                // Field lastCameraSectionZ:I
     159: aload_0
     160: ldc2_w        #106                // double 4.9E-324d
     163: putfield      #108                // Field prevCamX:D
     166: aload_0
     167: ldc2_w        #106                // double 4.9E-324d
     170: putfield      #112                // Field prevCamY:D
     173: aload_0
     174: ldc2_w        #106                // double 4.9E-324d
     177: putfield      #115                // Field prevCamZ:D
     180: aload_0
     181: ldc2_w        #106                // double 4.9E-324d
     184: putfield      #118                // Field prevCamRotX:D
     187: aload_0
     188: ldc2_w        #106                // double 4.9E-324d
     191: putfield      #121                // Field prevCamRotY:D
     194: aload_0
     195: iconst_m1
     196: putfield      #124                // Field lastViewDistance:I
     199: aload_0
     200: new           #127                // class net/minecraft/gizmos/SimpleGizmoCollector
     203: dup
     204: invokespecial #129                // Method net/minecraft/gizmos/SimpleGizmoCollector."<init>":()V
     207: putfield      #130                // Field collectedGizmos:Lnet/minecraft/gizmos/SimpleGizmoCollector;
     210: aload_0
     211: new           #134                // class net/minecraft/client/renderer/LevelRenderer$FinalizedGizmos
     214: dup
     215: new           #136                // class net/minecraft/client/renderer/gizmos/DrawableGizmoPrimitives
     218: dup
     219: invokespecial #138                // Method net/minecraft/client/renderer/gizmos/DrawableGizmoPrimitives."<init>":()V
     222: new           #136                // class net/minecraft/client/renderer/gizmos/DrawableGizmoPrimitives
     225: dup
     226: invokespecial #138                // Method net/minecraft/client/renderer/gizmos/DrawableGizmoPrimitives."<init>":()V
     229: invokespecial #139                // Method net/minecraft/client/renderer/LevelRenderer$FinalizedGizmos."<init>":(Lnet/minecraft/client/renderer/gizmos/DrawableGizmoPrimitives;Lnet/minecraft/client/renderer/gizmos/DrawableGizmoPrimitives;)V
     232: putfield      #142                // Field finalizedGizmos:Lnet/minecraft/client/renderer/LevelRenderer$FinalizedGizmos;
     235: aload_0
     236: aload_1
     237: putfield      #146                // Field minecraft:Lnet/minecraft/client/Minecraft;
     240: aload_0
     241: aload_2
     242: putfield      #150                // Field entityRenderDispatcher:Lnet/minecraft/client/renderer/entity/EntityRenderDispatcher;
     245: aload_0
     246: aload_3
     247: putfield      #154                // Field blockEntityRenderDispatcher:Lnet/minecraft/client/renderer/blockentity/BlockEntityRenderDispatcher;
     250: aload_0
     251: aload         4
     253: putfield      #158                // Field renderBuffers:Lnet/minecraft/client/renderer/RenderBuffers;
     256: aload_0
     257: aload         6
     259: invokevirtual #162                // Method net/minecraft/client/renderer/feature/FeatureRenderDispatcher.getSubmitNodeStorage:()Lnet/minecraft/client/renderer/SubmitNodeStorage;
     262: putfield      #168                // Field submitNodeStorage:Lnet/minecraft/client/renderer/SubmitNodeStorage;
     265: aload_0
     266: aload         5
     268: putfield      #172                // Field levelRenderState:Lnet/minecraft/client/renderer/state/LevelRenderState;
     271: aload_0
     272: aload         6
     274: putfield      #176                // Field featureRenderDispatcher:Lnet/minecraft/client/renderer/feature/FeatureRenderDispatcher;
     277: return

  public void close();
    Code:
       0: aload_0
       1: getfield      #180                // Field entityOutlineTarget:Lcom/mojang/blaze3d/pipeline/RenderTarget;
       4: ifnull        14
       7: aload_0
       8: getfield      #180                // Field entityOutlineTarget:Lcom/mojang/blaze3d/pipeline/RenderTarget;
      11: invokevirtual #184                // Method com/mojang/blaze3d/pipeline/RenderTarget.destroyBuffers:()V
      14: aload_0
      15: getfield      #189                // Field skyRenderer:Lnet/minecraft/client/renderer/SkyRenderer;
      18: ifnull        28
      21: aload_0
      22: getfield      #189                // Field skyRenderer:Lnet/minecraft/client/renderer/SkyRenderer;
      25: invokevirtual #193                // Method net/minecraft/client/renderer/SkyRenderer.close:()V
      28: aload_0
      29: getfield      #198                // Field chunkLayerSampler:Lcom/mojang/blaze3d/textures/GpuSampler;
      32: ifnull        42
      35: aload_0
      36: getfield      #198                // Field chunkLayerSampler:Lcom/mojang/blaze3d/textures/GpuSampler;
      39: invokevirtual #202                // Method com/mojang/blaze3d/textures/GpuSampler.close:()V
      42: aload_0
      43: getfield      #10                 // Field cloudRenderer:Lnet/minecraft/client/renderer/CloudRenderer;
      46: invokevirtual #205                // Method net/minecraft/client/renderer/CloudRenderer.close:()V
      49: return

  public void onResourceManagerReload(net.minecraft.server.packs.resources.ResourceManager);
    Code:
       0: aload_0
       1: invokevirtual #206                // Method initOutline:()V
       4: aload_0
       5: getfield      #189                // Field skyRenderer:Lnet/minecraft/client/renderer/SkyRenderer;
       8: ifnull        18
      11: aload_0
      12: getfield      #189                // Field skyRenderer:Lnet/minecraft/client/renderer/SkyRenderer;
      15: invokevirtual #193                // Method net/minecraft/client/renderer/SkyRenderer.close:()V
      18: aload_0
      19: new           #194                // class net/minecraft/client/renderer/SkyRenderer
      22: dup
      23: aload_0
      24: getfield      #146                // Field minecraft:Lnet/minecraft/client/Minecraft;
      27: invokevirtual #209                // Method net/minecraft/client/Minecraft.getTextureManager:()Lnet/minecraft/client/renderer/texture/TextureManager;
      30: aload_0
      31: getfield      #146                // Field minecraft:Lnet/minecraft/client/Minecraft;
      34: invokevirtual #215                // Method net/minecraft/client/Minecraft.getAtlasManager:()Lnet/minecraft/client/resources/model/AtlasManager;
      37: invokespecial #219                // Method net/minecraft/client/renderer/SkyRenderer."<init>":(Lnet/minecraft/client/renderer/texture/TextureManager;Lnet/minecraft/client/resources/model/AtlasManager;)V
      40: putfield      #189                // Field skyRenderer:Lnet/minecraft/client/renderer/SkyRenderer;
      43: return

  public void initOutline();
    Code:
       0: aload_0
       1: getfield      #180                // Field entityOutlineTarget:Lcom/mojang/blaze3d/pipeline/RenderTarget;
       4: ifnull        14
       7: aload_0
       8: getfield      #180                // Field entityOutlineTarget:Lcom/mojang/blaze3d/pipeline/RenderTarget;
      11: invokevirtual #184                // Method com/mojang/blaze3d/pipeline/RenderTarget.destroyBuffers:()V
      14: aload_0
      15: new           #222                // class com/mojang/blaze3d/pipeline/TextureTarget
      18: dup
      19: ldc           #224                // String Entity Outline
      21: aload_0
      22: getfield      #146                // Field minecraft:Lnet/minecraft/client/Minecraft;
      25: invokevirtual #226                // Method net/minecraft/client/Minecraft.getWindow:()Lcom/mojang/blaze3d/platform/Window;
      28: invokevirtual #230                // Method com/mojang/blaze3d/platform/Window.getWidth:()I
      31: aload_0
      32: getfield      #146                // Field minecraft:Lnet/minecraft/client/Minecraft;
      35: invokevirtual #226                // Method net/minecraft/client/Minecraft.getWindow:()Lcom/mojang/blaze3d/platform/Window;
      38: invokevirtual #236                // Method com/mojang/blaze3d/platform/Window.getHeight:()I
      41: iconst_1
      42: invokespecial #239                // Method com/mojang/blaze3d/pipeline/TextureTarget."<init>":(Ljava/lang/String;IIZ)V
      45: putfield      #180                // Field entityOutlineTarget:Lcom/mojang/blaze3d/pipeline/RenderTarget;
      48: return

  public void doEntityOutline();
    Code:
       0: aload_0
       1: invokevirtual #289                // Method shouldShowEntityOutlines:()Z
       4: ifeq          24
       7: aload_0
       8: getfield      #180                // Field entityOutlineTarget:Lcom/mojang/blaze3d/pipeline/RenderTarget;
      11: aload_0
      12: getfield      #146                // Field minecraft:Lnet/minecraft/client/Minecraft;
      15: invokevirtual #292                // Method net/minecraft/client/Minecraft.getMainRenderTarget:()Lcom/mojang/blaze3d/pipeline/RenderTarget;
      18: invokevirtual #296                // Method com/mojang/blaze3d/pipeline/RenderTarget.getColorTextureView:()Lcom/mojang/blaze3d/textures/GpuTextureView;
      21: invokevirtual #300                // Method com/mojang/blaze3d/pipeline/RenderTarget.blitAndBlendToTexture:(Lcom/mojang/blaze3d/textures/GpuTextureView;)V
      24: return

  public boolean shouldShowEntityOutlines();
    Code:
       0: aload_0
       1: getfield      #146                // Field minecraft:Lnet/minecraft/client/Minecraft;
       4: getfield      #304                // Field net/minecraft/client/Minecraft.gameRenderer:Lnet/minecraft/client/renderer/GameRenderer;
       7: invokevirtual #308                // Method net/minecraft/client/renderer/GameRenderer.isPanoramicMode:()Z
      10: ifne          34
      13: aload_0
      14: getfield      #180                // Field entityOutlineTarget:Lcom/mojang/blaze3d/pipeline/RenderTarget;
      17: ifnull        34
      20: aload_0
      21: getfield      #146                // Field minecraft:Lnet/minecraft/client/Minecraft;
      24: getfield      #313                // Field net/minecraft/client/Minecraft.player:Lnet/minecraft/client/player/LocalPlayer;
      27: ifnull        34
      30: iconst_1
      31: goto          35
      34: iconst_0
      35: ireturn

  public void setLevel(net.minecraft.client.multiplayer.ClientLevel);
    Code:
       0: aload_0
       1: ldc           #93                 // int -2147483648
       3: putfield      #94                 // Field lastCameraSectionX:I
       6: aload_0
       7: ldc           #93                 // int -2147483648
       9: putfield      #98                 // Field lastCameraSectionY:I
      12: aload_0
      13: ldc           #93                 // int -2147483648
      15: putfield      #101                // Field lastCameraSectionZ:I
      18: aload_0
      19: aload_1
      20: putfield      #317                // Field level:Lnet/minecraft/client/multiplayer/ClientLevel;
      23: aload_1
      24: ifnull        34
      27: aload_0
      28: invokevirtual #321                // Method allChanged:()V
      31: goto          91
      34: aload_0
      35: getfield      #150                // Field entityRenderDispatcher:Lnet/minecraft/client/renderer/entity/EntityRenderDispatcher;
      38: invokevirtual #324                // Method net/minecraft/client/renderer/entity/EntityRenderDispatcher.resetCamera:()V
      41: aload_0
      42: getfield      #329                // Field viewArea:Lnet/minecraft/client/renderer/ViewArea;
      45: ifnull        60
      48: aload_0
      49: getfield      #329                // Field viewArea:Lnet/minecraft/client/renderer/ViewArea;
      52: invokevirtual #333                // Method net/minecraft/client/renderer/ViewArea.releaseAllBuffers:()V
      55: aload_0
      56: aconst_null
      57: putfield      #329                // Field viewArea:Lnet/minecraft/client/renderer/ViewArea;
      60: aload_0
      61: getfield      #338                // Field sectionRenderDispatcher:Lnet/minecraft/client/renderer/chunk/SectionRenderDispatcher;
      64: ifnull        74
      67: aload_0
      68: getfield      #338                // Field sectionRenderDispatcher:Lnet/minecraft/client/renderer/chunk/SectionRenderDispatcher;
      71: invokevirtual #342                // Method net/minecraft/client/renderer/chunk/SectionRenderDispatcher.dispose:()V
      74: aload_0
      75: aconst_null
      76: putfield      #338                // Field sectionRenderDispatcher:Lnet/minecraft/client/renderer/chunk/SectionRenderDispatcher;
      79: aload_0
      80: getfield      #54                 // Field sectionOcclusionGraph:Lnet/minecraft/client/renderer/SectionOcclusionGraph;
      83: aconst_null
      84: invokevirtual #347                // Method net/minecraft/client/renderer/SectionOcclusionGraph.waitAndReset:(Lnet/minecraft/client/renderer/ViewArea;)V
      87: aload_0
      88: invokevirtual #351                // Method clearVisibleSections:()V
      91: aload_0
      92: getfield      #47                 // Field gameTestBlockHighlightRenderer:Lnet/minecraft/client/renderer/debug/GameTestBlockHighlightRenderer;
      95: invokevirtual #354                // Method net/minecraft/client/renderer/debug/GameTestBlockHighlightRenderer.clear:()V
      98: return

  public void allChanged();
    Code:
       0: aload_0
       1: getfield      #317                // Field level:Lnet/minecraft/client/multiplayer/ClientLevel;
       4: ifnull        228
       7: aload_0
       8: getfield      #317                // Field level:Lnet/minecraft/client/multiplayer/ClientLevel;
      11: invokevirtual #358                // Method net/minecraft/client/multiplayer/ClientLevel.clearTintCaches:()V
      14: aload_0
      15: getfield      #338                // Field sectionRenderDispatcher:Lnet/minecraft/client/renderer/chunk/SectionRenderDispatcher;
      18: ifnonnull     61
      21: aload_0
      22: new           #343                // class net/minecraft/client/renderer/chunk/SectionRenderDispatcher
      25: dup
      26: aload_0
      27: getfield      #317                // Field level:Lnet/minecraft/client/multiplayer/ClientLevel;
      30: aload_0
      31: invokestatic  #363                // Method net/minecraft/util/Util.backgroundExecutor:()Lnet/minecraft/TracingExecutor;
      34: aload_0
      35: getfield      #158                // Field renderBuffers:Lnet/minecraft/client/renderer/RenderBuffers;
      38: aload_0
      39: getfield      #146                // Field minecraft:Lnet/minecraft/client/Minecraft;
      42: invokevirtual #369                // Method net/minecraft/client/Minecraft.getBlockRenderer:()Lnet/minecraft/client/renderer/block/BlockRenderDispatcher;
      45: aload_0
      46: getfield      #146                // Field minecraft:Lnet/minecraft/client/Minecraft;
      49: invokevirtual #373                // Method net/minecraft/client/Minecraft.getBlockEntityRenderDispatcher:()Lnet/minecraft/client/renderer/blockentity/BlockEntityRenderDispatcher;
      52: invokespecial #377                // Method net/minecraft/client/renderer/chunk/SectionRenderDispatcher."<init>":(Lnet/minecraft/client/multiplayer/ClientLevel;Lnet/minecraft/client/renderer/LevelRenderer;Lnet/minecraft/TracingExecutor;Lnet/minecraft/client/renderer/RenderBuffers;Lnet/minecraft/client/renderer/block/BlockRenderDispatcher;Lnet/minecraft/client/renderer/blockentity/BlockEntityRenderDispatcher;)V
      55: putfield      #338                // Field sectionRenderDispatcher:Lnet/minecraft/client/renderer/chunk/SectionRenderDispatcher;
      58: goto          72
      61: aload_0
      62: getfield      #338                // Field sectionRenderDispatcher:Lnet/minecraft/client/renderer/chunk/SectionRenderDispatcher;
      65: aload_0
      66: getfield      #317                // Field level:Lnet/minecraft/client/multiplayer/ClientLevel;
      69: invokevirtual #380                // Method net/minecraft/client/renderer/chunk/SectionRenderDispatcher.setLevel:(Lnet/minecraft/client/multiplayer/ClientLevel;)V
      72: aload_0
      73: getfield      #10                 // Field cloudRenderer:Lnet/minecraft/client/renderer/CloudRenderer;
      76: invokevirtual #384                // Method net/minecraft/client/renderer/CloudRenderer.markForRebuild:()V
      79: aload_0
      80: getfield      #146                // Field minecraft:Lnet/minecraft/client/Minecraft;
      83: getfield      #264                // Field net/minecraft/client/Minecraft.options:Lnet/minecraft/client/Options;
      86: invokevirtual #387                // Method net/minecraft/client/Options.cutoutLeaves:()Lnet/minecraft/client/OptionInstance;
      89: invokevirtual #390                // Method net/minecraft/client/OptionInstance.get:()Ljava/lang/Object;
      92: checkcast     #275                // class java/lang/Boolean
      95: invokevirtual #394                // Method java/lang/Boolean.booleanValue:()Z
      98: invokestatic  #397                // Method net/minecraft/client/renderer/ItemBlockRenderTypes.setCutoutLeaves:(Z)V
     101: aload_0
     102: getfield      #146                // Field minecraft:Lnet/minecraft/client/Minecraft;
     105: getfield      #264                // Field net/minecraft/client/Minecraft.options:Lnet/minecraft/client/Options;
     108: invokevirtual #387                // Method net/minecraft/client/Options.cutoutLeaves:()Lnet/minecraft/client/OptionInstance;
     111: invokevirtual #390                // Method net/minecraft/client/OptionInstance.get:()Ljava/lang/Object;
     114: checkcast     #275                // class java/lang/Boolean
     117: invokevirtual #394                // Method java/lang/Boolean.booleanValue:()Z
     120: invokestatic  #403                // Method net/minecraft/world/level/block/LeavesBlock.setCutoutLeaves:(Z)V
     123: aload_0
     124: aload_0
     125: getfield      #146                // Field minecraft:Lnet/minecraft/client/Minecraft;
     128: getfield      #264                // Field net/minecraft/client/Minecraft.options:Lnet/minecraft/client/Options;
     131: invokevirtual #406                // Method net/minecraft/client/Options.getEffectiveRenderDistance:()I
     134: putfield      #124                // Field lastViewDistance:I
     137: aload_0
     138: getfield      #329                // Field viewArea:Lnet/minecraft/client/renderer/ViewArea;
     141: ifnull        151
     144: aload_0
     145: getfield      #329                // Field viewArea:Lnet/minecraft/client/renderer/ViewArea;
     148: invokevirtual #333                // Method net/minecraft/client/renderer/ViewArea.releaseAllBuffers:()V
     151: aload_0
     152: getfield      #338                // Field sectionRenderDispatcher:Lnet/minecraft/client/renderer/chunk/SectionRenderDispatcher;
     155: invokevirtual #409                // Method net/minecraft/client/renderer/chunk/SectionRenderDispatcher.clearCompileQueue:()V
     158: aload_0
     159: new           #334                // class net/minecraft/client/renderer/ViewArea
     162: dup
     163: aload_0
     164: getfield      #338                // Field sectionRenderDispatcher:Lnet/minecraft/client/renderer/chunk/SectionRenderDispatcher;
     167: aload_0
     168: getfield      #317                // Field level:Lnet/minecraft/client/multiplayer/ClientLevel;
     171: aload_0
     172: getfield      #146                // Field minecraft:Lnet/minecraft/client/Minecraft;
     175: getfield      #264                // Field net/minecraft/client/Minecraft.options:Lnet/minecraft/client/Options;
     178: invokevirtual #406                // Method net/minecraft/client/Options.getEffectiveRenderDistance:()I
     181: aload_0
     182: invokespecial #412                // Method net/minecraft/client/renderer/ViewArea."<init>":(Lnet/minecraft/client/renderer/chunk/SectionRenderDispatcher;Lnet/minecraft/world/level/Level;ILnet/minecraft/client/renderer/LevelRenderer;)V
     185: putfield      #329                // Field viewArea:Lnet/minecraft/client/renderer/ViewArea;
     188: aload_0
     189: getfield      #54                 // Field sectionOcclusionGraph:Lnet/minecraft/client/renderer/SectionOcclusionGraph;
     192: aload_0
     193: getfield      #329                // Field viewArea:Lnet/minecraft/client/renderer/ViewArea;
     196: invokevirtual #347                // Method net/minecraft/client/renderer/SectionOcclusionGraph.waitAndReset:(Lnet/minecraft/client/renderer/ViewArea;)V
     199: aload_0
     200: invokevirtual #351                // Method clearVisibleSections:()V
     203: aload_0
     204: getfield      #146                // Field minecraft:Lnet/minecraft/client/Minecraft;
     207: getfield      #304                // Field net/minecraft/client/Minecraft.gameRenderer:Lnet/minecraft/client/renderer/GameRenderer;
     210: invokevirtual #415                // Method net/minecraft/client/renderer/GameRenderer.getMainCamera:()Lnet/minecraft/client/Camera;
     213: astore_1
     214: aload_0
     215: getfield      #329                // Field viewArea:Lnet/minecraft/client/renderer/ViewArea;
     218: aload_1
     219: invokevirtual #419                // Method net/minecraft/client/Camera.position:()Lnet/minecraft/world/phys/Vec3;
     222: invokestatic  #425                // Method net/minecraft/core/SectionPos.of:(Lnet/minecraft/core/Position;)Lnet/minecraft/core/SectionPos;
     225: invokevirtual #431                // Method net/minecraft/client/renderer/ViewArea.repositionCamera:(Lnet/minecraft/core/SectionPos;)V
     228: return

  public void resize(int, int);
    Code:
       0: aload_0
       1: invokevirtual #435                // Method needsUpdate:()V
       4: aload_0
       5: getfield      #180                // Field entityOutlineTarget:Lcom/mojang/blaze3d/pipeline/RenderTarget;
       8: ifnull        20
      11: aload_0
      12: getfield      #180                // Field entityOutlineTarget:Lcom/mojang/blaze3d/pipeline/RenderTarget;
      15: iload_1
      16: iload_2
      17: invokevirtual #438                // Method com/mojang/blaze3d/pipeline/RenderTarget.resize:(II)V
      20: return

  public java.lang.String getSectionStatistics();
    Code:
       0: aload_0
       1: getfield      #329                // Field viewArea:Lnet/minecraft/client/renderer/ViewArea;
       4: ifnonnull     9
       7: aconst_null
       8: areturn
       9: aload_0
      10: getfield      #329                // Field viewArea:Lnet/minecraft/client/renderer/ViewArea;
      13: getfield      #442                // Field net/minecraft/client/renderer/ViewArea.sections:[Lnet/minecraft/client/renderer/chunk/SectionRenderDispatcher$RenderSection;
      16: arraylength
      17: istore_1
      18: aload_0
      19: invokevirtual #446                // Method countRenderedSections:()I
      22: istore_2
      23: getstatic     #449                // Field java/util/Locale.ROOT:Ljava/util/Locale;
      26: ldc_w         #455                // String C: %d/%d %sD: %d, %s
      29: iconst_5
      30: anewarray     #2                  // class java/lang/Object
      33: dup
      34: iconst_0
      35: iload_2
      36: invokestatic  #457                // Method java/lang/Integer.valueOf:(I)Ljava/lang/Integer;
      39: aastore
      40: dup
      41: iconst_1
      42: iload_1
      43: invokestatic  #457                // Method java/lang/Integer.valueOf:(I)Ljava/lang/Integer;
      46: aastore
      47: dup
      48: iconst_2
      49: aload_0
      50: getfield      #146                // Field minecraft:Lnet/minecraft/client/Minecraft;
      53: getfield      #460                // Field net/minecraft/client/Minecraft.smartCull:Z
      56: ifeq          65
      59: ldc_w         #464                // String (s)
      62: goto          68
      65: ldc_w         #466                // String
      68: aastore
      69: dup
      70: iconst_3
      71: aload_0
      72: getfield      #124                // Field lastViewDistance:I
      75: invokestatic  #457                // Method java/lang/Integer.valueOf:(I)Ljava/lang/Integer;
      78: aastore
      79: dup
      80: iconst_4
      81: aload_0
      82: getfield      #338                // Field sectionRenderDispatcher:Lnet/minecraft/client/renderer/chunk/SectionRenderDispatcher;
      85: ifnonnull     94
      88: ldc_w         #468                // String null
      91: goto          101
      94: aload_0
      95: getfield      #338                // Field sectionRenderDispatcher:Lnet/minecraft/client/renderer/chunk/SectionRenderDispatcher;
      98: invokevirtual #470                // Method net/minecraft/client/renderer/chunk/SectionRenderDispatcher.getStats:()Ljava/lang/String;
     101: aastore
     102: invokestatic  #474                // Method java/lang/String.format:(Ljava/util/Locale;Ljava/lang/String;[Ljava/lang/Object;)Ljava/lang/String;
     105: areturn

  public net.minecraft.client.renderer.chunk.SectionRenderDispatcher getSectionRenderDispatcher();
    Code:
       0: aload_0
       1: getfield      #338                // Field sectionRenderDispatcher:Lnet/minecraft/client/renderer/chunk/SectionRenderDispatcher;
       4: areturn

  public double getTotalSections();
    Code:
       0: aload_0
       1: getfield      #329                // Field viewArea:Lnet/minecraft/client/renderer/ViewArea;
       4: ifnonnull     11
       7: dconst_0
       8: goto          20
      11: aload_0
      12: getfield      #329                // Field viewArea:Lnet/minecraft/client/renderer/ViewArea;
      15: getfield      #442                // Field net/minecraft/client/renderer/ViewArea.sections:[Lnet/minecraft/client/renderer/chunk/SectionRenderDispatcher$RenderSection;
      18: arraylength
      19: i2d
      20: dreturn

  public double getLastViewDistance();
    Code:
       0: aload_0
       1: getfield      #124                // Field lastViewDistance:I
       4: i2d
       5: dreturn

  public int countRenderedSections();
    Code:
       0: iconst_0
       1: istore_1
       2: aload_0
       3: getfield      #63                 // Field visibleSections:Lit/unimi/dsi/fastutil/objects/ObjectArrayList;
       6: invokevirtual #480                // Method it/unimi/dsi/fastutil/objects/ObjectArrayList.iterator:()Lit/unimi/dsi/fastutil/objects/ObjectListIterator;
       9: astore_2
      10: aload_2
      11: invokeinterface #484,  1          // InterfaceMethod java/util/Iterator.hasNext:()Z
      16: ifeq          47
      19: aload_2
      20: invokeinterface #489,  1          // InterfaceMethod java/util/Iterator.next:()Ljava/lang/Object;
      25: checkcast     #492                // class net/minecraft/client/renderer/chunk/SectionRenderDispatcher$RenderSection
      28: astore_3
      29: aload_3
      30: invokevirtual #494                // Method net/minecraft/client/renderer/chunk/SectionRenderDispatcher$RenderSection.getSectionMesh:()Lnet/minecraft/client/renderer/chunk/SectionMesh;
      33: invokeinterface #498,  1          // InterfaceMethod net/minecraft/client/renderer/chunk/SectionMesh.hasRenderableLayers:()Z
      38: ifeq          44
      41: iinc          1, 1
      44: goto          10
      47: iload_1
      48: ireturn

  public void resetSampler();
    Code:
       0: aload_0
       1: getfield      #198                // Field chunkLayerSampler:Lcom/mojang/blaze3d/textures/GpuSampler;
       4: ifnull        14
       7: aload_0
       8: getfield      #198                // Field chunkLayerSampler:Lcom/mojang/blaze3d/textures/GpuSampler;
      11: invokevirtual #202                // Method com/mojang/blaze3d/textures/GpuSampler.close:()V
      14: aload_0
      15: aconst_null
      16: putfield      #198                // Field chunkLayerSampler:Lcom/mojang/blaze3d/textures/GpuSampler;
      19: return

  public java.lang.String getEntityStatistics();
    Code:
       0: aload_0
       1: getfield      #317                // Field level:Lnet/minecraft/client/multiplayer/ClientLevel;
       4: ifnonnull     11
       7: aconst_null
       8: goto          42
      11: aload_0
      12: getfield      #172                // Field levelRenderState:Lnet/minecraft/client/renderer/state/LevelRenderState;
      15: getfield      #503                // Field net/minecraft/client/renderer/state/LevelRenderState.entityRenderStates:Ljava/util/List;
      18: invokeinterface #509,  1          // InterfaceMethod java/util/List.size:()I
      23: aload_0
      24: getfield      #317                // Field level:Lnet/minecraft/client/multiplayer/ClientLevel;
      27: invokevirtual #514                // Method net/minecraft/client/multiplayer/ClientLevel.getEntityCount:()I
      30: aload_0
      31: getfield      #317                // Field level:Lnet/minecraft/client/multiplayer/ClientLevel;
      34: invokevirtual #517                // Method net/minecraft/client/multiplayer/ClientLevel.getServerSimulationDistance:()I
      37: invokedynamic #520,  0            // InvokeDynamic #0:makeConcatWithConstants:(III)Ljava/lang/String;
      42: areturn

  public static net.minecraft.client.renderer.culling.Frustum offsetFrustum(net.minecraft.client.renderer.culling.Frustum);
    Code:
       0: new           #629                // class net/minecraft/client/renderer/culling/Frustum
       3: dup
       4: aload_0
       5: invokespecial #631                // Method net/minecraft/client/renderer/culling/Frustum."<init>":(Lnet/minecraft/client/renderer/culling/Frustum;)V
       8: bipush        8
      10: invokevirtual #633                // Method net/minecraft/client/renderer/culling/Frustum.offsetToFullyIncludeCameraCube:(I)Lnet/minecraft/client/renderer/culling/Frustum;
      13: areturn

  public void addRecentlyCompiledSection(net.minecraft.client.renderer.chunk.SectionRenderDispatcher$RenderSection);
    Code:
       0: aload_0
       1: getfield      #54                 // Field sectionOcclusionGraph:Lnet/minecraft/client/renderer/SectionOcclusionGraph;
       4: aload_1
       5: invokevirtual #664                // Method net/minecraft/client/renderer/SectionOcclusionGraph.schedulePropagationFrom:(Lnet/minecraft/client/renderer/chunk/SectionRenderDispatcher$RenderSection;)V
       8: return

  public void renderLevel(com.mojang.blaze3d.resource.GraphicsResourceAllocator, net.minecraft.client.DeltaTracker, boolean, net.minecraft.client.Camera, org.joml.Matrix4f, org.joml.Matrix4f, org.joml.Matrix4f, com.mojang.blaze3d.buffers.GpuBufferSlice, org.joml.Vector4f, boolean);
    Code:
       0: aload_2
       1: iconst_0
       2: invokeinterface #678,  2          // InterfaceMethod net/minecraft/client/DeltaTracker.getGameTimeDeltaPartialTick:(Z)F
       7: fstore        11
       9: aload_0
      10: getfield      #172                // Field levelRenderState:Lnet/minecraft/client/renderer/state/LevelRenderState;
      13: aload_0
      14: getfield      #317                // Field level:Lnet/minecraft/client/multiplayer/ClientLevel;
      17: invokevirtual #684                // Method net/minecraft/client/multiplayer/ClientLevel.getGameTime:()J
      20: putfield      #688                // Field net/minecraft/client/renderer/state/LevelRenderState.gameTime:J
      23: aload_0
      24: getfield      #154                // Field blockEntityRenderDispatcher:Lnet/minecraft/client/renderer/blockentity/BlockEntityRenderDispatcher;
      27: aload         4
      29: invokevirtual #692                // Method net/minecraft/client/renderer/blockentity/BlockEntityRenderDispatcher.prepare:(Lnet/minecraft/client/Camera;)V
      32: aload_0
      33: getfield      #150                // Field entityRenderDispatcher:Lnet/minecraft/client/renderer/entity/EntityRenderDispatcher;
      36: aload         4
      38: aload_0
      39: getfield      #146                // Field minecraft:Lnet/minecraft/client/Minecraft;
      42: getfield      #697                // Field net/minecraft/client/Minecraft.crosshairPickEntity:Lnet/minecraft/world/entity/Entity;
      45: invokevirtual #701                // Method net/minecraft/client/renderer/entity/EntityRenderDispatcher.prepare:(Lnet/minecraft/client/Camera;Lnet/minecraft/world/entity/Entity;)V
      48: invokestatic  #524                // Method net/minecraft/util/profiling/Profiler.get:()Lnet/minecraft/util/profiling/ProfilerFiller;
      51: astore        12
      53: aload         12
      55: ldc_w         #704                // String populateLightUpdates
      58: invokeinterface #530,  2          // InterfaceMethod net/minecraft/util/profiling/ProfilerFiller.push:(Ljava/lang/String;)V
      63: aload_0
      64: getfield      #317                // Field level:Lnet/minecraft/client/multiplayer/ClientLevel;
      67: invokevirtual #706                // Method net/minecraft/client/multiplayer/ClientLevel.pollLightUpdates:()V
      70: aload         12
      72: ldc_w         #709                // String runLightUpdates
      75: invokeinterface #711,  2          // InterfaceMethod net/minecraft/util/profiling/ProfilerFiller.popPush:(Ljava/lang/String;)V
      80: aload_0
      81: getfield      #317                // Field level:Lnet/minecraft/client/multiplayer/ClientLevel;
      84: invokevirtual #596                // Method net/minecraft/client/multiplayer/ClientLevel.getChunkSource:()Lnet/minecraft/client/multiplayer/ClientChunkCache;
      87: invokevirtual #714                // Method net/minecraft/client/multiplayer/ClientChunkCache.getLightEngine:()Lnet/minecraft/world/level/lighting/LevelLightEngine;
      90: invokevirtual #718                // Method net/minecraft/world/level/lighting/LevelLightEngine.runLightUpdates:()I
      93: pop
      94: aload         12
      96: ldc_w         #722                // String prepareCullFrustum
      99: invokeinterface #711,  2          // InterfaceMethod net/minecraft/util/profiling/ProfilerFiller.popPush:(Ljava/lang/String;)V
     104: aload         4
     106: invokevirtual #419                // Method net/minecraft/client/Camera.position:()Lnet/minecraft/world/phys/Vec3;
     109: astore        13
     111: aload_0
     112: aload         5
     114: aload         7
     116: aload         13
     118: invokevirtual #724                // Method prepareCullFrustum:(Lorg/joml/Matrix4f;Lorg/joml/Matrix4f;Lnet/minecraft/world/phys/Vec3;)Lnet/minecraft/client/renderer/culling/Frustum;
     121: astore        14
     123: aload         12
     125: ldc_w         #727                // String cullTerrain
     128: invokeinterface #711,  2          // InterfaceMethod net/minecraft/util/profiling/ProfilerFiller.popPush:(Ljava/lang/String;)V
     133: aload_0
     134: aload         4
     136: aload         14
     138: aload_0
     139: getfield      #146                // Field minecraft:Lnet/minecraft/client/Minecraft;
     142: getfield      #313                // Field net/minecraft/client/Minecraft.player:Lnet/minecraft/client/player/LocalPlayer;
     145: invokevirtual #729                // Method net/minecraft/client/player/LocalPlayer.isSpectator:()Z
     148: invokevirtual #734                // Method cullTerrain:(Lnet/minecraft/client/Camera;Lnet/minecraft/client/renderer/culling/Frustum;Z)V
     151: aload         12
     153: ldc_w         #737                // String compileSections
     156: invokeinterface #711,  2          // InterfaceMethod net/minecraft/util/profiling/ProfilerFiller.popPush:(Ljava/lang/String;)V
     161: aload_0
     162: aload         4
     164: invokevirtual #739                // Method compileSections:(Lnet/minecraft/client/Camera;)V
     167: aload         12
     169: ldc_w         #741                // String extract
     172: invokeinterface #711,  2          // InterfaceMethod net/minecraft/util/profiling/ProfilerFiller.popPush:(Ljava/lang/String;)V
     177: aload         12
     179: ldc_w         #743                // String entities
     182: invokeinterface #530,  2          // InterfaceMethod net/minecraft/util/profiling/ProfilerFiller.push:(Ljava/lang/String;)V
     187: aload_0
     188: aload         4
     190: aload         14
     192: aload_2
     193: aload_0
     194: getfield      #172                // Field levelRenderState:Lnet/minecraft/client/renderer/state/LevelRenderState;
     197: invokevirtual #745                // Method extractVisibleEntities:(Lnet/minecraft/client/Camera;Lnet/minecraft/client/renderer/culling/Frustum;Lnet/minecraft/client/DeltaTracker;Lnet/minecraft/client/renderer/state/LevelRenderState;)V
     200: aload         12
     202: ldc_w         #749                // String blockEntities
     205: invokeinterface #711,  2          // InterfaceMethod net/minecraft/util/profiling/ProfilerFiller.popPush:(Ljava/lang/String;)V
     210: aload_0
     211: aload         4
     213: fload         11
     215: aload_0
     216: getfield      #172                // Field levelRenderState:Lnet/minecraft/client/renderer/state/LevelRenderState;
     219: aload         14
     221: invokevirtual #751                // Method extractVisibleBlockEntities:(Lnet/minecraft/client/Camera;FLnet/minecraft/client/renderer/state/LevelRenderState;Lnet/minecraft/client/renderer/culling/Frustum;)V
     224: aload         12
     226: ldc_w         #755                // String blockOutline
     229: invokeinterface #711,  2          // InterfaceMethod net/minecraft/util/profiling/ProfilerFiller.popPush:(Ljava/lang/String;)V
     234: aload_0
     235: aload         4
     237: aload_0
     238: getfield      #172                // Field levelRenderState:Lnet/minecraft/client/renderer/state/LevelRenderState;
     241: invokevirtual #757                // Method extractBlockOutline:(Lnet/minecraft/client/Camera;Lnet/minecraft/client/renderer/state/LevelRenderState;)V
     244: aload         12
     246: ldc_w         #761                // String blockBreaking
     249: invokeinterface #711,  2          // InterfaceMethod net/minecraft/util/profiling/ProfilerFiller.popPush:(Ljava/lang/String;)V
     254: aload_0
     255: aload         4
     257: aload_0
     258: getfield      #172                // Field levelRenderState:Lnet/minecraft/client/renderer/state/LevelRenderState;
     261: invokevirtual #763                // Method extractBlockDestroyAnimation:(Lnet/minecraft/client/Camera;Lnet/minecraft/client/renderer/state/LevelRenderState;)V
     264: aload         12
     266: ldc_w         #766                // String weather
     269: invokeinterface #711,  2          // InterfaceMethod net/minecraft/util/profiling/ProfilerFiller.popPush:(Ljava/lang/String;)V
     274: aload_0
     275: getfield      #26                 // Field weatherEffectRenderer:Lnet/minecraft/client/renderer/WeatherEffectRenderer;
     278: aload_0
     279: getfield      #317                // Field level:Lnet/minecraft/client/multiplayer/ClientLevel;
     282: aload_0
     283: getfield      #768                // Field ticks:I
     286: fload         11
     288: aload         13
     290: aload_0
     291: getfield      #172                // Field levelRenderState:Lnet/minecraft/client/renderer/state/LevelRenderState;
     294: getfield      #771                // Field net/minecraft/client/renderer/state/LevelRenderState.weatherRenderState:Lnet/minecraft/client/renderer/state/WeatherRenderState;
     297: invokevirtual #775                // Method net/minecraft/client/renderer/WeatherEffectRenderer.extractRenderState:(Lnet/minecraft/world/level/Level;IFLnet/minecraft/world/phys/Vec3;Lnet/minecraft/client/renderer/state/WeatherRenderState;)V
     300: aload         12
     302: ldc_w         #779                // String sky
     305: invokeinterface #711,  2          // InterfaceMethod net/minecraft/util/profiling/ProfilerFiller.popPush:(Ljava/lang/String;)V
     310: aload_0
     311: getfield      #189                // Field skyRenderer:Lnet/minecraft/client/renderer/SkyRenderer;
     314: aload_0
     315: getfield      #317                // Field level:Lnet/minecraft/client/multiplayer/ClientLevel;
     318: fload         11
     320: aload         4
     322: aload_0
     323: getfield      #172                // Field levelRenderState:Lnet/minecraft/client/renderer/state/LevelRenderState;
     326: getfield      #781                // Field net/minecraft/client/renderer/state/LevelRenderState.skyRenderState:Lnet/minecraft/client/renderer/state/SkyRenderState;
     329: invokevirtual #785                // Method net/minecraft/client/renderer/SkyRenderer.extractRenderState:(Lnet/minecraft/client/multiplayer/ClientLevel;FLnet/minecraft/client/Camera;Lnet/minecraft/client/renderer/state/SkyRenderState;)V
     332: aload         12
     334: ldc_w         #788                // String border
     337: invokeinterface #711,  2          // InterfaceMethod net/minecraft/util/profiling/ProfilerFiller.popPush:(Ljava/lang/String;)V
     342: aload_0
     343: getfield      #19                 // Field worldBorderRenderer:Lnet/minecraft/client/renderer/WorldBorderRenderer;
     346: aload_0
     347: getfield      #317                // Field level:Lnet/minecraft/client/multiplayer/ClientLevel;
     350: invokevirtual #790                // Method net/minecraft/client/multiplayer/ClientLevel.getWorldBorder:()Lnet/minecraft/world/level/border/WorldBorder;
     353: fload         11
     355: aload         13
     357: aload_0
     358: getfield      #146                // Field minecraft:Lnet/minecraft/client/Minecraft;
     361: getfield      #264                // Field net/minecraft/client/Minecraft.options:Lnet/minecraft/client/Options;
     364: invokevirtual #406                // Method net/minecraft/client/Options.getEffectiveRenderDistance:()I
     367: bipush        16
     369: imul
     370: i2d
     371: aload_0
     372: getfield      #172                // Field levelRenderState:Lnet/minecraft/client/renderer/state/LevelRenderState;
     375: getfield      #794                // Field net/minecraft/client/renderer/state/LevelRenderState.worldBorderRenderState:Lnet/minecraft/client/renderer/state/WorldBorderRenderState;
     378: invokevirtual #798                // Method net/minecraft/client/renderer/WorldBorderRenderer.extract:(Lnet/minecraft/world/level/border/WorldBorder;FLnet/minecraft/world/phys/Vec3;DLnet/minecraft/client/renderer/state/WorldBorderRenderState;)V
     381: aload         12
     383: ldc_w         #801                // String neoforge_custom
     386: invokeinterface #711,  2          // InterfaceMethod net/minecraft/util/profiling/ProfilerFiller.popPush:(Ljava/lang/String;)V
     391: aload_0
     392: getfield      #172                // Field levelRenderState:Lnet/minecraft/client/renderer/state/LevelRenderState;
     395: aload_0
     396: getfield      #317                // Field level:Lnet/minecraft/client/multiplayer/ClientLevel;
     399: aload         4
     401: invokevirtual #419                // Method net/minecraft/client/Camera.position:()Lnet/minecraft/world/phys/Vec3;
     404: invokestatic  #803                // Method net/neoforged/neoforge/client/CustomEnvironmentEffectsRendererManager.getCustomWeatherEffectRenderer:(Lnet/minecraft/world/level/Level;Lnet/minecraft/world/phys/Vec3;)Lnet/neoforged/neoforge/client/CustomWeatherEffectRenderer;
     407: putfield      #809                // Field net/minecraft/client/renderer/state/LevelRenderState.customWeatherEffectRenderer:Lnet/neoforged/neoforge/client/CustomWeatherEffectRenderer;
     410: aload_0
     411: getfield      #172                // Field levelRenderState:Lnet/minecraft/client/renderer/state/LevelRenderState;
     414: aload_0
     415: getfield      #317                // Field level:Lnet/minecraft/client/multiplayer/ClientLevel;
     418: aload         4
     420: invokevirtual #419                // Method net/minecraft/client/Camera.position:()Lnet/minecraft/world/phys/Vec3;
     423: invokestatic  #813                // Method net/neoforged/neoforge/client/CustomEnvironmentEffectsRendererManager.getCustomSkyboxRenderer:(Lnet/minecraft/world/level/Level;Lnet/minecraft/world/phys/Vec3;)Lnet/neoforged/neoforge/client/CustomSkyboxRenderer;
     426: putfield      #817                // Field net/minecraft/client/renderer/state/LevelRenderState.customSkyboxRenderer:Lnet/neoforged/neoforge/client/CustomSkyboxRenderer;
     429: aload_0
     430: getfield      #172                // Field levelRenderState:Lnet/minecraft/client/renderer/state/LevelRenderState;
     433: aload_0
     434: getfield      #317                // Field level:Lnet/minecraft/client/multiplayer/ClientLevel;
     437: aload         4
     439: invokevirtual #419                // Method net/minecraft/client/Camera.position:()Lnet/minecraft/world/phys/Vec3;
     442: invokestatic  #821                // Method net/neoforged/neoforge/client/CustomEnvironmentEffectsRendererManager.getCustomCloudsRenderer:(Lnet/minecraft/world/level/Level;Lnet/minecraft/world/phys/Vec3;)Lnet/neoforged/neoforge/client/CustomCloudsRenderer;
     445: putfield      #825                // Field net/minecraft/client/renderer/state/LevelRenderState.customCloudsRenderer:Lnet/neoforged/neoforge/client/CustomCloudsRenderer;
     448: getstatic     #829                // Field net/neoforged/neoforge/common/NeoForge.EVENT_BUS:Lnet/neoforged/bus/api/IEventBus;
     451: new           #835                // class net/neoforged/neoforge/client/event/ExtractLevelRenderStateEvent
     454: dup
     455: aload_0
     456: aload_0
     457: getfield      #172                // Field levelRenderState:Lnet/minecraft/client/renderer/state/LevelRenderState;
     460: aload_0
     461: getfield      #317                // Field level:Lnet/minecraft/client/multiplayer/ClientLevel;
     464: aload         4
     466: aload         14
     468: aload_2
     469: aload_0
     470: getfield      #768                // Field ticks:I
     473: invokespecial #837                // Method net/neoforged/neoforge/client/event/ExtractLevelRenderStateEvent."<init>":(Lnet/minecraft/client/renderer/LevelRenderer;Lnet/minecraft/client/renderer/state/LevelRenderState;Lnet/minecraft/client/multiplayer/ClientLevel;Lnet/minecraft/client/Camera;Lnet/minecraft/client/renderer/culling/Frustum;Lnet/minecraft/client/DeltaTracker;I)V
     476: invokeinterface #840,  2          // InterfaceMethod net/neoforged/bus/api/IEventBus.post:(Lnet/neoforged/bus/api/Event;)Lnet/neoforged/bus/api/Event;
     481: pop
     482: aload         12
     484: invokeinterface #574,  1          // InterfaceMethod net/minecraft/util/profiling/ProfilerFiller.pop:()V
     489: aload         12
     491: ldc_w         #846                // String debug
     494: invokeinterface #711,  2          // InterfaceMethod net/minecraft/util/profiling/ProfilerFiller.popPush:(Ljava/lang/String;)V
     499: aload_0
     500: getfield      #40                 // Field debugRenderer:Lnet/minecraft/client/renderer/debug/DebugRenderer;
     503: aload         14
     505: aload         13
     507: getfield      #559                // Field net/minecraft/world/phys/Vec3.x:D
     510: aload         13
     512: getfield      #569                // Field net/minecraft/world/phys/Vec3.y:D
     515: aload         13
     517: getfield      #571                // Field net/minecraft/world/phys/Vec3.z:D
     520: aload_2
     521: iconst_0
     522: invokeinterface #678,  2          // InterfaceMethod net/minecraft/client/DeltaTracker.getGameTimeDeltaPartialTick:(Z)F
     527: invokevirtual #848                // Method net/minecraft/client/renderer/debug/DebugRenderer.emitGizmos:(Lnet/minecraft/client/renderer/culling/Frustum;DDDF)V
     530: aload_0
     531: getfield      #47                 // Field gameTestBlockHighlightRenderer:Lnet/minecraft/client/renderer/debug/GameTestBlockHighlightRenderer;
     534: invokevirtual #852                // Method net/minecraft/client/renderer/debug/GameTestBlockHighlightRenderer.emitGizmos:()V
     537: aload         12
     539: ldc_w         #854                // String setupFrameGraph
     542: invokeinterface #711,  2          // InterfaceMethod net/minecraft/util/profiling/ProfilerFiller.popPush:(Ljava/lang/String;)V
     547: invokestatic  #856                // Method com/mojang/blaze3d/systems/RenderSystem.getModelViewStack:()Lorg/joml/Matrix4fStack;
     550: astore        15
     552: aload         15
     554: invokevirtual #862                // Method org/joml/Matrix4fStack.pushMatrix:()Lorg/joml/Matrix4fStack;
     557: pop
     558: aload         15
     560: aload         5
     562: invokevirtual #867                // Method org/joml/Matrix4fStack.mul:(Lorg/joml/Matrix4fc;)Lorg/joml/Matrix4f;
     565: pop
     566: new           #871                // class com/mojang/blaze3d/framegraph/FrameGraphBuilder
     569: dup
     570: invokespecial #873                // Method com/mojang/blaze3d/framegraph/FrameGraphBuilder."<init>":()V
     573: astore        16
     575: aload_0
     576: getfield      #87                 // Field targets:Lnet/minecraft/client/renderer/LevelTargetBundle;
     579: aload         16
     581: ldc_w         #874                // String main
     584: aload_0
     585: getfield      #146                // Field minecraft:Lnet/minecraft/client/Minecraft;
     588: invokevirtual #292                // Method net/minecraft/client/Minecraft.getMainRenderTarget:()Lcom/mojang/blaze3d/pipeline/RenderTarget;
     591: invokevirtual #876                // Method com/mojang/blaze3d/framegraph/FrameGraphBuilder.importExternal:(Ljava/lang/String;Ljava/lang/Object;)Lcom/mojang/blaze3d/resource/ResourceHandle;
     594: putfield      #880                // Field net/minecraft/client/renderer/LevelTargetBundle.main:Lcom/mojang/blaze3d/resource/ResourceHandle;
     597: aload_0
     598: getfield      #146                // Field minecraft:Lnet/minecraft/client/Minecraft;
     601: invokevirtual #292                // Method net/minecraft/client/Minecraft.getMainRenderTarget:()Lcom/mojang/blaze3d/pipeline/RenderTarget;
     604: getfield      #883                // Field com/mojang/blaze3d/pipeline/RenderTarget.width:I
     607: istore        17
     609: aload_0
     610: getfield      #146                // Field minecraft:Lnet/minecraft/client/Minecraft;
     613: invokevirtual #292                // Method net/minecraft/client/Minecraft.getMainRenderTarget:()Lcom/mojang/blaze3d/pipeline/RenderTarget;
     616: getfield      #886                // Field com/mojang/blaze3d/pipeline/RenderTarget.height:I
     619: istore        18
     621: new           #889                // class com/mojang/blaze3d/resource/RenderTargetDescriptor
     624: dup
     625: iload         17
     627: iload         18
     629: iconst_1
     630: iconst_0
     631: aload_0
     632: getfield      #146                // Field minecraft:Lnet/minecraft/client/Minecraft;
     635: invokevirtual #292                // Method net/minecraft/client/Minecraft.getMainRenderTarget:()Lcom/mojang/blaze3d/pipeline/RenderTarget;
     638: getfield      #891                // Field com/mojang/blaze3d/pipeline/RenderTarget.useStencil:Z
     641: invokespecial #894                // Method com/mojang/blaze3d/resource/RenderTargetDescriptor."<init>":(IIZIZ)V
     644: astore        19
     646: aload_0
     647: invokevirtual #897                // Method getTransparencyChain:()Lnet/minecraft/client/renderer/PostChain;
     650: astore        20
     652: aload         20
     654: ifnull        742
     657: aload_0
     658: getfield      #87                 // Field targets:Lnet/minecraft/client/renderer/LevelTargetBundle;
     661: aload         16
     663: ldc_w         #901                // String translucent
     666: aload         19
     668: invokevirtual #903                // Method com/mojang/blaze3d/framegraph/FrameGraphBuilder.createInternal:(Ljava/lang/String;Lcom/mojang/blaze3d/resource/ResourceDescriptor;)Lcom/mojang/blaze3d/resource/ResourceHandle;
     671: putfield      #907                // Field net/minecraft/client/renderer/LevelTargetBundle.translucent:Lcom/mojang/blaze3d/resource/ResourceHandle;
     674: aload_0
     675: getfield      #87                 // Field targets:Lnet/minecraft/client/renderer/LevelTargetBundle;
     678: aload         16
     680: ldc_w         #909                // String item_entity
     683: aload         19
     685: invokevirtual #903                // Method com/mojang/blaze3d/framegraph/FrameGraphBuilder.createInternal:(Ljava/lang/String;Lcom/mojang/blaze3d/resource/ResourceDescriptor;)Lcom/mojang/blaze3d/resource/ResourceHandle;
     688: putfield      #911                // Field net/minecraft/client/renderer/LevelTargetBundle.itemEntity:Lcom/mojang/blaze3d/resource/ResourceHandle;
     691: aload_0
     692: getfield      #87                 // Field targets:Lnet/minecraft/client/renderer/LevelTargetBundle;
     695: aload         16
     697: ldc_w         #914                // String particles
     700: aload         19
     702: invokevirtual #903                // Method com/mojang/blaze3d/framegraph/FrameGraphBuilder.createInternal:(Ljava/lang/String;Lcom/mojang/blaze3d/resource/ResourceDescriptor;)Lcom/mojang/blaze3d/resource/ResourceHandle;
     705: putfield      #916                // Field net/minecraft/client/renderer/LevelTargetBundle.particles:Lcom/mojang/blaze3d/resource/ResourceHandle;
     708: aload_0
     709: getfield      #87                 // Field targets:Lnet/minecraft/client/renderer/LevelTargetBundle;
     712: aload         16
     714: ldc_w         #766                // String weather
     717: aload         19
     719: invokevirtual #903                // Method com/mojang/blaze3d/framegraph/FrameGraphBuilder.createInternal:(Ljava/lang/String;Lcom/mojang/blaze3d/resource/ResourceDescriptor;)Lcom/mojang/blaze3d/resource/ResourceHandle;
     722: putfield      #918                // Field net/minecraft/client/renderer/LevelTargetBundle.weather:Lcom/mojang/blaze3d/resource/ResourceHandle;
     725: aload_0
     726: getfield      #87                 // Field targets:Lnet/minecraft/client/renderer/LevelTargetBundle;
     729: aload         16
     731: ldc_w         #920                // String clouds
     734: aload         19
     736: invokevirtual #903                // Method com/mojang/blaze3d/framegraph/FrameGraphBuilder.createInternal:(Ljava/lang/String;Lcom/mojang/blaze3d/resource/ResourceDescriptor;)Lcom/mojang/blaze3d/resource/ResourceHandle;
     739: putfield      #922                // Field net/minecraft/client/renderer/LevelTargetBundle.clouds:Lcom/mojang/blaze3d/resource/ResourceHandle;
     742: aload_0
     743: getfield      #180                // Field entityOutlineTarget:Lcom/mojang/blaze3d/pipeline/RenderTarget;
     746: ifnull        768
     749: aload_0
     750: getfield      #87                 // Field targets:Lnet/minecraft/client/renderer/LevelTargetBundle;
     753: aload         16
     755: ldc_w         #924                // String entity_outline
     758: aload_0
     759: getfield      #180                // Field entityOutlineTarget:Lcom/mojang/blaze3d/pipeline/RenderTarget;
     762: invokevirtual #876                // Method com/mojang/blaze3d/framegraph/FrameGraphBuilder.importExternal:(Ljava/lang/String;Ljava/lang/Object;)Lcom/mojang/blaze3d/resource/ResourceHandle;
     765: putfield      #926                // Field net/minecraft/client/renderer/LevelTargetBundle.entityOutline:Lcom/mojang/blaze3d/resource/ResourceHandle;
     768: aload         16
     770: aload_0
     771: getfield      #87                 // Field targets:Lnet/minecraft/client/renderer/LevelTargetBundle;
     774: aload         19
     776: aload         14
     778: aload         4
     780: aload         5
     782: aload         6
     784: aload_2
     785: aload         12
     787: invokestatic  #929                // Method net/neoforged/neoforge/client/ClientHooks.fireFrameGraphSetup:(Lcom/mojang/blaze3d/framegraph/FrameGraphBuilder;Lnet/minecraft/client/renderer/LevelTargetBundle;Lcom/mojang/blaze3d/resource/RenderTargetDescriptor;Lnet/minecraft/client/renderer/culling/Frustum;Lnet/minecraft/client/Camera;Lorg/joml/Matrix4f;Lorg/joml/Matrix4f;Lnet/minecraft/client/DeltaTracker;Lnet/minecraft/util/profiling/ProfilerFiller;)Lnet/neoforged/neoforge/client/event/FrameGraphSetupEvent;
     790: astore        21
     792: aload_0
     793: getfield      #172                // Field levelRenderState:Lnet/minecraft/client/renderer/state/LevelRenderState;
     796: dup
     797: getfield      #935                // Field net/minecraft/client/renderer/state/LevelRenderState.haveGlowingEntities:Z
     800: aload         21
     802: invokevirtual #938                // Method net/neoforged/neoforge/client/event/FrameGraphSetupEvent.isOutlineProcessingEnabled:()Z
     805: ior
     806: putfield      #935                // Field net/minecraft/client/renderer/state/LevelRenderState.haveGlowingEntities:Z
     809: aload         16
     811: ldc_w         #943                // String clear
     814: invokevirtual #944                // Method com/mojang/blaze3d/framegraph/FrameGraphBuilder.addPass:(Ljava/lang/String;)Lcom/mojang/blaze3d/framegraph/FramePass;
     817: astore        22
     819: aload_0
     820: getfield      #87                 // Field targets:Lnet/minecraft/client/renderer/LevelTargetBundle;
     823: aload         22
     825: aload_0
     826: getfield      #87                 // Field targets:Lnet/minecraft/client/renderer/LevelTargetBundle;
     829: getfield      #880                // Field net/minecraft/client/renderer/LevelTargetBundle.main:Lcom/mojang/blaze3d/resource/ResourceHandle;
     832: invokeinterface #948,  2          // InterfaceMethod com/mojang/blaze3d/framegraph/FramePass.readsAndWrites:(Lcom/mojang/blaze3d/resource/ResourceHandle;)Lcom/mojang/blaze3d/resource/ResourceHandle;
     837: putfield      #880                // Field net/minecraft/client/renderer/LevelTargetBundle.main:Lcom/mojang/blaze3d/resource/ResourceHandle;
     840: aload         22
     842: aload_0
     843: aload         9
     845: invokedynamic #954,  0            // InvokeDynamic #2:run:(Lnet/minecraft/client/renderer/LevelRenderer;Lorg/joml/Vector4f;)Ljava/lang/Runnable;
     850: invokeinterface #958,  2          // InterfaceMethod com/mojang/blaze3d/framegraph/FramePass.executes:(Ljava/lang/Runnable;)V
     855: iload         10
     857: ifeq          872
     860: aload_0
     861: aload         16
     863: aload         4
     865: aload         8
     867: aload         5
     869: invokevirtual #962                // Method addSkyPass:(Lcom/mojang/blaze3d/framegraph/FrameGraphBuilder;Lnet/minecraft/client/Camera;Lcom/mojang/blaze3d/buffers/GpuBufferSlice;Lorg/joml/Matrix4f;)V
     872: aload_0
     873: aload         16
     875: aload         14
     877: aload         5
     879: aload         8
     881: iload_3
     882: aload_0
     883: getfield      #172                // Field levelRenderState:Lnet/minecraft/client/renderer/state/LevelRenderState;
     886: aload_2
     887: aload         12
     889: invokevirtual #966                // Method addMainPass:(Lcom/mojang/blaze3d/framegraph/FrameGraphBuilder;Lnet/minecraft/client/renderer/culling/Frustum;Lorg/joml/Matrix4f;Lcom/mojang/blaze3d/buffers/GpuBufferSlice;ZLnet/minecraft/client/renderer/state/LevelRenderState;Lnet/minecraft/client/DeltaTracker;Lnet/minecraft/util/profiling/ProfilerFiller;)V
     892: aload_0
     893: getfield      #146                // Field minecraft:Lnet/minecraft/client/Minecraft;
     896: invokevirtual #246                // Method net/minecraft/client/Minecraft.getShaderManager:()Lnet/minecraft/client/renderer/ShaderManager;
     899: getstatic     #970                // Field ENTITY_OUTLINE_POST_CHAIN_ID:Lnet/minecraft/resources/Identifier;
     902: getstatic     #973                // Field net/minecraft/client/renderer/LevelTargetBundle.OUTLINE_TARGETS:Ljava/util/Set;
     905: invokevirtual #258                // Method net/minecraft/client/renderer/ShaderManager.getPostChain:(Lnet/minecraft/resources/Identifier;Ljava/util/Set;)Lnet/minecraft/client/renderer/PostChain;
     908: astore        23
     910: aload_0
     911: getfield      #172                // Field levelRenderState:Lnet/minecraft/client/renderer/state/LevelRenderState;
     914: getfield      #935                // Field net/minecraft/client/renderer/state/LevelRenderState.haveGlowingEntities:Z
     917: ifeq          940
     920: aload         23
     922: ifnull        940
     925: aload         23
     927: aload         16
     929: iload         17
     931: iload         18
     933: aload_0
     934: getfield      #87                 // Field targets:Lnet/minecraft/client/renderer/LevelTargetBundle;
     937: invokevirtual #976                // Method net/minecraft/client/renderer/PostChain.addToFrame:(Lcom/mojang/blaze3d/framegraph/FrameGraphBuilder;IILnet/minecraft/client/renderer/PostChain$TargetBundle;)V
     940: aload_0
     941: getfield      #146                // Field minecraft:Lnet/minecraft/client/Minecraft;
     944: getfield      #982                // Field net/minecraft/client/Minecraft.particleEngine:Lnet/minecraft/client/particle/ParticleEngine;
     947: aload_0
     948: getfield      #33                 // Field particlesRenderState:Lnet/minecraft/client/renderer/state/ParticlesRenderState;
     951: new           #629                // class net/minecraft/client/renderer/culling/Frustum
     954: dup
     955: aload         14
     957: invokespecial #631                // Method net/minecraft/client/renderer/culling/Frustum."<init>":(Lnet/minecraft/client/renderer/culling/Frustum;)V
     960: ldc_w         #986                // float -3.0f
     963: invokevirtual #987                // Method net/minecraft/client/renderer/culling/Frustum.offset:(F)Lnet/minecraft/client/renderer/culling/Frustum;
     966: aload         4
     968: fload         11
     970: invokevirtual #991                // Method net/minecraft/client/particle/ParticleEngine.extract:(Lnet/minecraft/client/renderer/state/ParticlesRenderState;Lnet/minecraft/client/renderer/culling/Frustum;Lnet/minecraft/client/Camera;F)V
     973: aload_0
     974: aload         16
     976: aload         8
     978: aload         5
     980: invokevirtual #996                // Method addParticlesPass:(Lcom/mojang/blaze3d/framegraph/FrameGraphBuilder;Lcom/mojang/blaze3d/buffers/GpuBufferSlice;Lorg/joml/Matrix4f;)V
     983: aload_0
     984: getfield      #146                // Field minecraft:Lnet/minecraft/client/Minecraft;
     987: getfield      #264                // Field net/minecraft/client/Minecraft.options:Lnet/minecraft/client/Options;
     990: invokevirtual #1000               // Method net/minecraft/client/Options.getCloudsType:()Lnet/minecraft/client/CloudStatus;
     993: astore        24
     995: aload         24
     997: getstatic     #1004               // Field net/minecraft/client/CloudStatus.OFF:Lnet/minecraft/client/CloudStatus;
    1000: if_acmpeq     1086
    1003: aload         4
    1005: invokevirtual #1010               // Method net/minecraft/client/Camera.attributeProbe:()Lnet/minecraft/world/attribute/EnvironmentAttributeProbe;
    1008: getstatic     #1014               // Field net/minecraft/world/attribute/EnvironmentAttributes.CLOUD_COLOR:Lnet/minecraft/world/attribute/EnvironmentAttribute;
    1011: fload         11
    1013: invokevirtual #1020               // Method net/minecraft/world/attribute/EnvironmentAttributeProbe.getValue:(Lnet/minecraft/world/attribute/EnvironmentAttribute;F)Ljava/lang/Object;
    1016: checkcast     #91                 // class java/lang/Integer
    1019: invokevirtual #1026               // Method java/lang/Integer.intValue:()I
    1022: istore        25
    1024: iload         25
    1026: invokestatic  #1029               // Method net/minecraft/util/ARGB.alpha:(I)I
    1029: ifle          1086
    1032: aload         4
    1034: invokevirtual #1010               // Method net/minecraft/client/Camera.attributeProbe:()Lnet/minecraft/world/attribute/EnvironmentAttributeProbe;
    1037: getstatic     #1035               // Field net/minecraft/world/attribute/EnvironmentAttributes.CLOUD_HEIGHT:Lnet/minecraft/world/attribute/EnvironmentAttribute;
    1040: fload         11
    1042: invokevirtual #1020               // Method net/minecraft/world/attribute/EnvironmentAttributeProbe.getValue:(Lnet/minecraft/world/attribute/EnvironmentAttribute;F)Ljava/lang/Object;
    1045: checkcast     #1038               // class java/lang/Float
    1048: invokevirtual #1040               // Method java/lang/Float.floatValue:()F
    1051: fstore        26
    1053: aload_0
    1054: aload         16
    1056: aload         24
    1058: aload_0
    1059: getfield      #172                // Field levelRenderState:Lnet/minecraft/client/renderer/state/LevelRenderState;
    1062: getfield      #1043               // Field net/minecraft/client/renderer/state/LevelRenderState.cameraRenderState:Lnet/minecraft/client/renderer/state/CameraRenderState;
    1065: getfield      #1047               // Field net/minecraft/client/renderer/state/CameraRenderState.pos:Lnet/minecraft/world/phys/Vec3;
    1068: aload_0
    1069: getfield      #172                // Field levelRenderState:Lnet/minecraft/client/renderer/state/LevelRenderState;
    1072: getfield      #688                // Field net/minecraft/client/renderer/state/LevelRenderState.gameTime:J
    1075: fload         11
    1077: iload         25
    1079: fload         26
    1081: aload         5
    1083: invokevirtual #1053               // Method addCloudsPass:(Lcom/mojang/blaze3d/framegraph/FrameGraphBuilder;Lnet/minecraft/client/CloudStatus;Lnet/minecraft/world/phys/Vec3;JFIFLorg/joml/Matrix4f;)V
    1086: aload_0
    1087: aload         16
    1089: aload         8
    1091: aload         5
    1093: invokevirtual #1057               // Method addWeatherPass:(Lcom/mojang/blaze3d/framegraph/FrameGraphBuilder;Lcom/mojang/blaze3d/buffers/GpuBufferSlice;Lorg/joml/Matrix4f;)V
    1096: aload         20
    1098: ifnull        1116
    1101: aload         20
    1103: aload         16
    1105: iload         17
    1107: iload         18
    1109: aload_0
    1110: getfield      #87                 // Field targets:Lnet/minecraft/client/renderer/LevelTargetBundle;
    1113: invokevirtual #976                // Method net/minecraft/client/renderer/PostChain.addToFrame:(Lcom/mojang/blaze3d/framegraph/FrameGraphBuilder;IILnet/minecraft/client/renderer/PostChain$TargetBundle;)V
    1116: aload_0
    1117: aload         16
    1119: aload_0
    1120: getfield      #172                // Field levelRenderState:Lnet/minecraft/client/renderer/state/LevelRenderState;
    1123: getfield      #1043               // Field net/minecraft/client/renderer/state/LevelRenderState.cameraRenderState:Lnet/minecraft/client/renderer/state/CameraRenderState;
    1126: aload         8
    1128: aload         5
    1130: invokevirtual #1060               // Method addLateDebugPass:(Lcom/mojang/blaze3d/framegraph/FrameGraphBuilder;Lnet/minecraft/client/renderer/state/CameraRenderState;Lcom/mojang/blaze3d/buffers/GpuBufferSlice;Lorg/joml/Matrix4f;)V
    1133: aload         12
    1135: ldc_w         #1064               // String executeFrameGraph
    1138: invokeinterface #711,  2          // InterfaceMethod net/minecraft/util/profiling/ProfilerFiller.popPush:(Ljava/lang/String;)V
    1143: aload         16
    1145: aload_1
    1146: new           #1066               // class net/minecraft/client/renderer/LevelRenderer$1
    1149: dup
    1150: aload_0
    1151: aload         12
    1153: invokespecial #1068               // Method net/minecraft/client/renderer/LevelRenderer$1."<init>":(Lnet/minecraft/client/renderer/LevelRenderer;Lnet/minecraft/util/profiling/ProfilerFiller;)V
    1156: invokevirtual #1071               // Method com/mojang/blaze3d/framegraph/FrameGraphBuilder.execute:(Lcom/mojang/blaze3d/resource/GraphicsResourceAllocator;Lcom/mojang/blaze3d/framegraph/FrameGraphBuilder$Inspector;)V
    1159: aload_0
    1160: getfield      #87                 // Field targets:Lnet/minecraft/client/renderer/LevelTargetBundle;
    1163: invokevirtual #1075               // Method net/minecraft/client/renderer/LevelTargetBundle.clear:()V
    1166: aload         15
    1168: invokevirtual #1076               // Method org/joml/Matrix4fStack.popMatrix:()Lorg/joml/Matrix4fStack;
    1171: pop
    1172: aload         12
    1174: invokeinterface #574,  1          // InterfaceMethod net/minecraft/util/profiling/ProfilerFiller.pop:()V
    1179: aload_0
    1180: getfield      #172                // Field levelRenderState:Lnet/minecraft/client/renderer/state/LevelRenderState;
    1183: invokevirtual #1079               // Method net/minecraft/client/renderer/state/LevelRenderState.reset:()V
    1186: return

  public void endFrame();
    Code:
       0: aload_0
       1: getfield      #10                 // Field cloudRenderer:Lnet/minecraft/client/renderer/CloudRenderer;
       4: invokevirtual #1680               // Method net/minecraft/client/renderer/CloudRenderer.endFrame:()V
       7: return

  public void captureFrustum();
    Code:
       0: aload_0
       1: iconst_1
       2: putfield      #668                // Field captureFrustum:Z
       5: return

  public void killFrustum();
    Code:
       0: aload_0
       1: aconst_null
       2: putfield      #577                // Field capturedFrustum:Lnet/minecraft/client/renderer/culling/Frustum;
       5: return

  public void tick(net.minecraft.client.Camera);
    Code:
       0: aload_0
       1: getfield      #317                // Field level:Lnet/minecraft/client/multiplayer/ClientLevel;
       4: invokevirtual #1111               // Method net/minecraft/client/multiplayer/ClientLevel.tickRateManager:()Lnet/minecraft/world/TickRateManager;
       7: invokevirtual #1683               // Method net/minecraft/world/TickRateManager.runsNormally:()Z
      10: ifeq          23
      13: aload_0
      14: dup
      15: getfield      #768                // Field ticks:I
      18: iconst_1
      19: iadd
      20: putfield      #768                // Field ticks:I
      23: aload_0
      24: getfield      #26                 // Field weatherEffectRenderer:Lnet/minecraft/client/renderer/WeatherEffectRenderer;
      27: aload_0
      28: getfield      #317                // Field level:Lnet/minecraft/client/multiplayer/ClientLevel;
      31: aload_1
      32: aload_0
      33: getfield      #768                // Field ticks:I
      36: aload_0
      37: getfield      #146                // Field minecraft:Lnet/minecraft/client/Minecraft;
      40: getfield      #264                // Field net/minecraft/client/Minecraft.options:Lnet/minecraft/client/Options;
      43: invokevirtual #1686               // Method net/minecraft/client/Options.particles:()Lnet/minecraft/client/OptionInstance;
      46: invokevirtual #390                // Method net/minecraft/client/OptionInstance.get:()Ljava/lang/Object;
      49: checkcast     #1688               // class net/minecraft/server/level/ParticleStatus
      52: aload_0
      53: getfield      #146                // Field minecraft:Lnet/minecraft/client/Minecraft;
      56: getfield      #264                // Field net/minecraft/client/Minecraft.options:Lnet/minecraft/client/Options;
      59: invokevirtual #1690               // Method net/minecraft/client/Options.weatherRadius:()Lnet/minecraft/client/OptionInstance;
      62: invokevirtual #390                // Method net/minecraft/client/OptionInstance.get:()Ljava/lang/Object;
      65: checkcast     #91                 // class java/lang/Integer
      68: invokevirtual #1026               // Method java/lang/Integer.intValue:()I
      71: invokevirtual #1693               // Method net/minecraft/client/renderer/WeatherEffectRenderer.tickRainParticles:(Lnet/minecraft/client/multiplayer/ClientLevel;Lnet/minecraft/client/Camera;ILnet/minecraft/server/level/ParticleStatus;I)V
      74: aload_0
      75: invokevirtual #1697               // Method removeBlockBreakingProgress:()V
      78: return

  public void blockChanged(net.minecraft.world.level.BlockGetter, net.minecraft.core.BlockPos, net.minecraft.world.level.block.state.BlockState, net.minecraft.world.level.block.state.BlockState, int);
    Code:
       0: aload_0
       1: aload_2
       2: iload         5
       4: bipush        8
       6: iand
       7: ifeq          14
      10: iconst_1
      11: goto          15
      14: iconst_0
      15: invokevirtual #1884               // Method setBlockDirty:(Lnet/minecraft/core/BlockPos;Z)V
      18: return

  public void setBlocksDirty(int, int, int, int, int, int);
    Code:
       0: iload_3
       1: iconst_1
       2: isub
       3: istore        7
       5: iload         7
       7: iload         6
       9: iconst_1
      10: iadd
      11: if_icmpgt     79
      14: iload_1
      15: iconst_1
      16: isub
      17: istore        8
      19: iload         8
      21: iload         4
      23: iconst_1
      24: iadd
      25: if_icmpgt     73
      28: iload_2
      29: iconst_1
      30: isub
      31: istore        9
      33: iload         9
      35: iload         5
      37: iconst_1
      38: iadd
      39: if_icmpgt     67
      42: aload_0
      43: iload         8
      45: invokestatic  #1888               // Method net/minecraft/core/SectionPos.blockToSectionCoord:(I)I
      48: iload         9
      50: invokestatic  #1888               // Method net/minecraft/core/SectionPos.blockToSectionCoord:(I)I
      53: iload         7
      55: invokestatic  #1888               // Method net/minecraft/core/SectionPos.blockToSectionCoord:(I)I
      58: invokevirtual #1895               // Method setSectionDirty:(III)V
      61: iinc          9, 1
      64: goto          33
      67: iinc          8, 1
      70: goto          19
      73: iinc          7, 1
      76: goto          5
      79: return

  public void setBlockDirty(net.minecraft.core.BlockPos, net.minecraft.world.level.block.state.BlockState, net.minecraft.world.level.block.state.BlockState);
    Code:
       0: aload_0
       1: getfield      #146                // Field minecraft:Lnet/minecraft/client/Minecraft;
       4: invokevirtual #1898               // Method net/minecraft/client/Minecraft.getModelManager:()Lnet/minecraft/client/resources/model/ModelManager;
       7: aload_2
       8: aload_3
       9: invokevirtual #1902               // Method net/minecraft/client/resources/model/ModelManager.requiresRender:(Lnet/minecraft/world/level/block/state/BlockState;Lnet/minecraft/world/level/block/state/BlockState;)Z
      12: ifeq          43
      15: aload_0
      16: aload_1
      17: invokevirtual #1268               // Method net/minecraft/core/BlockPos.getX:()I
      20: aload_1
      21: invokevirtual #1153               // Method net/minecraft/core/BlockPos.getY:()I
      24: aload_1
      25: invokevirtual #1270               // Method net/minecraft/core/BlockPos.getZ:()I
      28: aload_1
      29: invokevirtual #1268               // Method net/minecraft/core/BlockPos.getX:()I
      32: aload_1
      33: invokevirtual #1153               // Method net/minecraft/core/BlockPos.getY:()I
      36: aload_1
      37: invokevirtual #1270               // Method net/minecraft/core/BlockPos.getZ:()I
      40: invokevirtual #1908               // Method setBlocksDirty:(IIIIII)V
      43: return

  public void setSectionDirtyWithNeighbors(int, int, int);
    Code:
       0: aload_0
       1: iload_1
       2: iconst_1
       3: isub
       4: iload_2
       5: iconst_1
       6: isub
       7: iload_3
       8: iconst_1
       9: isub
      10: iload_1
      11: iconst_1
      12: iadd
      13: iload_2
      14: iconst_1
      15: iadd
      16: iload_3
      17: iconst_1
      18: iadd
      19: invokevirtual #1912               // Method setSectionRangeDirty:(IIIIII)V
      22: return

  public void setSectionRangeDirty(int, int, int, int, int, int);
    Code:
       0: iload_3
       1: istore        7
       3: iload         7
       5: iload         6
       7: if_icmpgt     58
      10: iload_1
      11: istore        8
      13: iload         8
      15: iload         4
      17: if_icmpgt     52
      20: iload_2
      21: istore        9
      23: iload         9
      25: iload         5
      27: if_icmpgt     46
      30: aload_0
      31: iload         8
      33: iload         9
      35: iload         7
      37: invokevirtual #1895               // Method setSectionDirty:(III)V
      40: iinc          9, 1
      43: goto          23
      46: iinc          8, 1
      49: goto          13
      52: iinc          7, 1
      55: goto          3
      58: return

  public void setSectionDirty(int, int, int);
    Code:
       0: aload_0
       1: iload_1
       2: iload_2
       3: iload_3
       4: iconst_0
       5: invokevirtual #1891               // Method setSectionDirty:(IIIZ)V
       8: return

  public void onSectionBecomingNonEmpty(long);
    Code:
       0: aload_0
       1: getfield      #329                // Field viewArea:Lnet/minecraft/client/renderer/ViewArea;
       4: lload_1
       5: invokevirtual #1918               // Method net/minecraft/client/renderer/ViewArea.getRenderSection:(J)Lnet/minecraft/client/renderer/chunk/SectionRenderDispatcher$RenderSection;
       8: astore_3
       9: aload_3
      10: ifnull        26
      13: aload_0
      14: getfield      #54                 // Field sectionOcclusionGraph:Lnet/minecraft/client/renderer/SectionOcclusionGraph;
      17: aload_3
      18: invokevirtual #664                // Method net/minecraft/client/renderer/SectionOcclusionGraph.schedulePropagationFrom:(Lnet/minecraft/client/renderer/chunk/SectionRenderDispatcher$RenderSection;)V
      21: aload_3
      22: iconst_1
      23: invokevirtual #1831               // Method net/minecraft/client/renderer/chunk/SectionRenderDispatcher$RenderSection.setWasPreviouslyEmpty:(Z)V
      26: return

  public void destroyBlockProgress(int, net.minecraft.core.BlockPos, int);
    Code:
       0: iload_3
       1: iflt          161
       4: iload_3
       5: bipush        10
       7: if_icmpge     161
      10: aload_0
      11: getfield      #73                 // Field destroyingBlocks:Lit/unimi/dsi/fastutil/ints/Int2ObjectMap;
      14: iload_1
      15: invokeinterface #1922,  2         // InterfaceMethod it/unimi/dsi/fastutil/ints/Int2ObjectMap.get:(I)Ljava/lang/Object;
      20: checkcast     #1280               // class net/minecraft/server/level/BlockDestructionProgress
      23: astore        4
      25: aload         4
      27: ifnull        36
      30: aload_0
      31: aload         4
      33: invokevirtual #1711               // Method removeProgress:(Lnet/minecraft/server/level/BlockDestructionProgress;)V
      36: aload         4
      38: ifnull        86
      41: aload         4
      43: invokevirtual #1715               // Method net/minecraft/server/level/BlockDestructionProgress.getPos:()Lnet/minecraft/core/BlockPos;
      46: invokevirtual #1268               // Method net/minecraft/core/BlockPos.getX:()I
      49: aload_2
      50: invokevirtual #1268               // Method net/minecraft/core/BlockPos.getX:()I
      53: if_icmpne     86
      56: aload         4
      58: invokevirtual #1715               // Method net/minecraft/server/level/BlockDestructionProgress.getPos:()Lnet/minecraft/core/BlockPos;
      61: invokevirtual #1153               // Method net/minecraft/core/BlockPos.getY:()I
      64: aload_2
      65: invokevirtual #1153               // Method net/minecraft/core/BlockPos.getY:()I
      68: if_icmpne     86
      71: aload         4
      73: invokevirtual #1715               // Method net/minecraft/server/level/BlockDestructionProgress.getPos:()Lnet/minecraft/core/BlockPos;
      76: invokevirtual #1270               // Method net/minecraft/core/BlockPos.getZ:()I
      79: aload_2
      80: invokevirtual #1270               // Method net/minecraft/core/BlockPos.getZ:()I
      83: if_icmpeq     110
      86: new           #1280               // class net/minecraft/server/level/BlockDestructionProgress
      89: dup
      90: iload_1
      91: aload_2
      92: invokespecial #1923               // Method net/minecraft/server/level/BlockDestructionProgress."<init>":(ILnet/minecraft/core/BlockPos;)V
      95: astore        4
      97: aload_0
      98: getfield      #73                 // Field destroyingBlocks:Lit/unimi/dsi/fastutil/ints/Int2ObjectMap;
     101: iload_1
     102: aload         4
     104: invokeinterface #1926,  3         // InterfaceMethod it/unimi/dsi/fastutil/ints/Int2ObjectMap.put:(ILjava/lang/Object;)Ljava/lang/Object;
     109: pop
     110: aload         4
     112: iload_3
     113: invokevirtual #1929               // Method net/minecraft/server/level/BlockDestructionProgress.setProgress:(I)V
     116: aload         4
     118: aload_0
     119: getfield      #768                // Field ticks:I
     122: invokevirtual #1932               // Method net/minecraft/server/level/BlockDestructionProgress.updateTick:(I)V
     125: aload_0
     126: getfield      #80                 // Field destructionProgress:Lit/unimi/dsi/fastutil/longs/Long2ObjectMap;
     129: aload         4
     131: invokevirtual #1715               // Method net/minecraft/server/level/BlockDestructionProgress.getPos:()Lnet/minecraft/core/BlockPos;
     134: invokevirtual #1254               // Method net/minecraft/core/BlockPos.asLong:()J
     137: invokedynamic #1935,  0           // InvokeDynamic #10:get:()Lit/unimi/dsi/fastutil/longs/Long2ObjectFunction;
     142: invokeinterface #1938,  4         // InterfaceMethod it/unimi/dsi/fastutil/longs/Long2ObjectMap.computeIfAbsent:(JLit/unimi/dsi/fastutil/longs/Long2ObjectFunction;)Ljava/lang/Object;
     147: checkcast     #1262               // class java/util/SortedSet
     150: aload         4
     152: invokeinterface #1942,  2         // InterfaceMethod java/util/SortedSet.add:(Ljava/lang/Object;)Z
     157: pop
     158: goto          187
     161: aload_0
     162: getfield      #73                 // Field destroyingBlocks:Lit/unimi/dsi/fastutil/ints/Int2ObjectMap;
     165: iload_1
     166: invokeinterface #1943,  2         // InterfaceMethod it/unimi/dsi/fastutil/ints/Int2ObjectMap.remove:(I)Ljava/lang/Object;
     171: checkcast     #1280               // class net/minecraft/server/level/BlockDestructionProgress
     174: astore        4
     176: aload         4
     178: ifnull        187
     181: aload_0
     182: aload         4
     184: invokevirtual #1711               // Method removeProgress:(Lnet/minecraft/server/level/BlockDestructionProgress;)V
     187: return

  public boolean hasRenderedAllSections();
    Code:
       0: aload_0
       1: getfield      #338                // Field sectionRenderDispatcher:Lnet/minecraft/client/renderer/chunk/SectionRenderDispatcher;
       4: invokevirtual #1945               // Method net/minecraft/client/renderer/chunk/SectionRenderDispatcher.isQueueEmpty:()Z
       7: ireturn

  public void onChunkReadyToRender(net.minecraft.world.level.ChunkPos);
    Code:
       0: aload_0
       1: getfield      #54                 // Field sectionOcclusionGraph:Lnet/minecraft/client/renderer/SectionOcclusionGraph;
       4: aload_1
       5: invokevirtual #1948               // Method net/minecraft/client/renderer/SectionOcclusionGraph.onChunkReadyToRender:(Lnet/minecraft/world/level/ChunkPos;)V
       8: return

  public void needsUpdate();
    Code:
       0: aload_0
       1: getfield      #54                 // Field sectionOcclusionGraph:Lnet/minecraft/client/renderer/SectionOcclusionGraph;
       4: invokevirtual #573                // Method net/minecraft/client/renderer/SectionOcclusionGraph.invalidate:()V
       7: aload_0
       8: getfield      #10                 // Field cloudRenderer:Lnet/minecraft/client/renderer/CloudRenderer;
      11: invokevirtual #384                // Method net/minecraft/client/renderer/CloudRenderer.markForRebuild:()V
      14: return

  public static int getLightColor(net.minecraft.world.level.BlockAndTintGetter, net.minecraft.core.BlockPos);
    Code:
       0: getstatic     #1952               // Field net/minecraft/client/renderer/LevelRenderer$BrightnessGetter.DEFAULT:Lnet/minecraft/client/renderer/LevelRenderer$BrightnessGetter;
       3: aload_0
       4: aload_0
       5: aload_1
       6: invokeinterface #1958,  2         // InterfaceMethod net/minecraft/world/level/BlockAndTintGetter.getBlockState:(Lnet/minecraft/core/BlockPos;)Lnet/minecraft/world/level/block/state/BlockState;
      11: aload_1
      12: invokestatic  #1961               // Method getLightColor:(Lnet/minecraft/client/renderer/LevelRenderer$BrightnessGetter;Lnet/minecraft/world/level/BlockAndTintGetter;Lnet/minecraft/world/level/block/state/BlockState;Lnet/minecraft/core/BlockPos;)I
      15: ireturn

  public static int getLightColor(net.minecraft.client.renderer.LevelRenderer$BrightnessGetter, net.minecraft.world.level.BlockAndTintGetter, net.minecraft.world.level.block.state.BlockState, net.minecraft.core.BlockPos);
    Code:
       0: aload_2
       1: aload_1
       2: aload_3
       3: invokevirtual #1965               // Method net/minecraft/world/level/block/state/BlockState.emissiveRendering:(Lnet/minecraft/world/level/BlockGetter;Lnet/minecraft/core/BlockPos;)Z
       6: ifeq          13
       9: ldc_w         #1969               // int 15728880
      12: ireturn
      13: aload_0
      14: aload_1
      15: aload_3
      16: invokeinterface #1970,  3         // InterfaceMethod net/minecraft/client/renderer/LevelRenderer$BrightnessGetter.packedBrightness:(Lnet/minecraft/world/level/BlockAndTintGetter;Lnet/minecraft/core/BlockPos;)I
      21: istore        4
      23: iload         4
      25: invokestatic  #1974               // Method net/minecraft/client/renderer/LightTexture.block:(I)I
      28: istore        5
      30: aload_2
      31: aload_1
      32: aload_3
      33: invokevirtual #1979               // Method net/minecraft/world/level/block/state/BlockState.getLightEmission:(Lnet/minecraft/world/level/BlockGetter;Lnet/minecraft/core/BlockPos;)I
      36: istore        6
      38: iload         5
      40: iload         6
      42: if_icmpge     60
      45: iload         4
      47: invokestatic  #1983               // Method net/minecraft/client/renderer/LightTexture.sky:(I)I
      50: istore        7
      52: iload         6
      54: iload         7
      56: invokestatic  #1985               // Method net/minecraft/client/renderer/LightTexture.pack:(II)I
      59: ireturn
      60: iload         4
      62: ireturn

  public boolean isSectionCompiledAndVisible(net.minecraft.core.BlockPos);
    Code:
       0: aload_0
       1: getfield      #329                // Field viewArea:Lnet/minecraft/client/renderer/ViewArea;
       4: aload_1
       5: invokevirtual #1988               // Method net/minecraft/client/renderer/ViewArea.getRenderSectionAt:(Lnet/minecraft/core/BlockPos;)Lnet/minecraft/client/renderer/chunk/SectionRenderDispatcher$RenderSection;
       8: astore_2
       9: aload_2
      10: ifnull        48
      13: aload_2
      14: getfield      #1992               // Field net/minecraft/client/renderer/chunk/SectionRenderDispatcher$RenderSection.sectionMesh:Ljava/util/concurrent/atomic/AtomicReference;
      17: invokevirtual #1996               // Method java/util/concurrent/atomic/AtomicReference.get:()Ljava/lang/Object;
      20: getstatic     #1788               // Field net/minecraft/client/renderer/chunk/CompiledSectionMesh.UNCOMPILED:Lnet/minecraft/client/renderer/chunk/SectionMesh;
      23: if_acmpeq     48
      26: aload_2
      27: invokestatic  #1241               // Method net/minecraft/util/Util.getMillis:()J
      30: invokevirtual #1244               // Method net/minecraft/client/renderer/chunk/SectionRenderDispatcher$RenderSection.getVisibility:(J)F
      33: ldc_w         #1248               // float 0.3f
      36: fcmpl
      37: iflt          44
      40: iconst_1
      41: goto          49
      44: iconst_0
      45: goto          49
      48: iconst_0
      49: ireturn

  public com.mojang.blaze3d.pipeline.RenderTarget entityOutlineTarget();
    Code:
       0: aload_0
       1: getfield      #87                 // Field targets:Lnet/minecraft/client/renderer/LevelTargetBundle;
       4: getfield      #926                // Field net/minecraft/client/renderer/LevelTargetBundle.entityOutline:Lcom/mojang/blaze3d/resource/ResourceHandle;
       7: ifnull        28
      10: aload_0
      11: getfield      #87                 // Field targets:Lnet/minecraft/client/renderer/LevelTargetBundle;
      14: getfield      #926                // Field net/minecraft/client/renderer/LevelTargetBundle.entityOutline:Lcom/mojang/blaze3d/resource/ResourceHandle;
      17: invokeinterface #1999,  1         // InterfaceMethod com/mojang/blaze3d/resource/ResourceHandle.get:()Ljava/lang/Object;
      22: checkcast     #185                // class com/mojang/blaze3d/pipeline/RenderTarget
      25: goto          29
      28: aconst_null
      29: areturn

  public com.mojang.blaze3d.pipeline.RenderTarget getTranslucentTarget();
    Code:
       0: aload_0
       1: getfield      #87                 // Field targets:Lnet/minecraft/client/renderer/LevelTargetBundle;
       4: getfield      #907                // Field net/minecraft/client/renderer/LevelTargetBundle.translucent:Lcom/mojang/blaze3d/resource/ResourceHandle;
       7: ifnull        28
      10: aload_0
      11: getfield      #87                 // Field targets:Lnet/minecraft/client/renderer/LevelTargetBundle;
      14: getfield      #907                // Field net/minecraft/client/renderer/LevelTargetBundle.translucent:Lcom/mojang/blaze3d/resource/ResourceHandle;
      17: invokeinterface #1999,  1         // InterfaceMethod com/mojang/blaze3d/resource/ResourceHandle.get:()Ljava/lang/Object;
      22: checkcast     #185                // class com/mojang/blaze3d/pipeline/RenderTarget
      25: goto          29
      28: aconst_null
      29: areturn

  public com.mojang.blaze3d.pipeline.RenderTarget getItemEntityTarget();
    Code:
       0: aload_0
       1: getfield      #87                 // Field targets:Lnet/minecraft/client/renderer/LevelTargetBundle;
       4: getfield      #911                // Field net/minecraft/client/renderer/LevelTargetBundle.itemEntity:Lcom/mojang/blaze3d/resource/ResourceHandle;
       7: ifnull        28
      10: aload_0
      11: getfield      #87                 // Field targets:Lnet/minecraft/client/renderer/LevelTargetBundle;
      14: getfield      #911                // Field net/minecraft/client/renderer/LevelTargetBundle.itemEntity:Lcom/mojang/blaze3d/resource/ResourceHandle;
      17: invokeinterface #1999,  1         // InterfaceMethod com/mojang/blaze3d/resource/ResourceHandle.get:()Ljava/lang/Object;
      22: checkcast     #185                // class com/mojang/blaze3d/pipeline/RenderTarget
      25: goto          29
      28: aconst_null
      29: areturn

  public com.mojang.blaze3d.pipeline.RenderTarget getParticlesTarget();
    Code:
       0: aload_0
       1: getfield      #87                 // Field targets:Lnet/minecraft/client/renderer/LevelTargetBundle;
       4: getfield      #916                // Field net/minecraft/client/renderer/LevelTargetBundle.particles:Lcom/mojang/blaze3d/resource/ResourceHandle;
       7: ifnull        28
      10: aload_0
      11: getfield      #87                 // Field targets:Lnet/minecraft/client/renderer/LevelTargetBundle;
      14: getfield      #916                // Field net/minecraft/client/renderer/LevelTargetBundle.particles:Lcom/mojang/blaze3d/resource/ResourceHandle;
      17: invokeinterface #1999,  1         // InterfaceMethod com/mojang/blaze3d/resource/ResourceHandle.get:()Ljava/lang/Object;
      22: checkcast     #185                // class com/mojang/blaze3d/pipeline/RenderTarget
      25: goto          29
      28: aconst_null
      29: areturn

  public com.mojang.blaze3d.pipeline.RenderTarget getWeatherTarget();
    Code:
       0: aload_0
       1: getfield      #87                 // Field targets:Lnet/minecraft/client/renderer/LevelTargetBundle;
       4: getfield      #918                // Field net/minecraft/client/renderer/LevelTargetBundle.weather:Lcom/mojang/blaze3d/resource/ResourceHandle;
       7: ifnull        28
      10: aload_0
      11: getfield      #87                 // Field targets:Lnet/minecraft/client/renderer/LevelTargetBundle;
      14: getfield      #918                // Field net/minecraft/client/renderer/LevelTargetBundle.weather:Lcom/mojang/blaze3d/resource/ResourceHandle;
      17: invokeinterface #1999,  1         // InterfaceMethod com/mojang/blaze3d/resource/ResourceHandle.get:()Ljava/lang/Object;
      22: checkcast     #185                // class com/mojang/blaze3d/pipeline/RenderTarget
      25: goto          29
      28: aconst_null
      29: areturn

  public com.mojang.blaze3d.pipeline.RenderTarget getCloudsTarget();
    Code:
       0: aload_0
       1: getfield      #87                 // Field targets:Lnet/minecraft/client/renderer/LevelTargetBundle;
       4: getfield      #922                // Field net/minecraft/client/renderer/LevelTargetBundle.clouds:Lcom/mojang/blaze3d/resource/ResourceHandle;
       7: ifnull        28
      10: aload_0
      11: getfield      #87                 // Field targets:Lnet/minecraft/client/renderer/LevelTargetBundle;
      14: getfield      #922                // Field net/minecraft/client/renderer/LevelTargetBundle.clouds:Lcom/mojang/blaze3d/resource/ResourceHandle;
      17: invokeinterface #1999,  1         // InterfaceMethod com/mojang/blaze3d/resource/ResourceHandle.get:()Ljava/lang/Object;
      22: checkcast     #185                // class com/mojang/blaze3d/pipeline/RenderTarget
      25: goto          29
      28: aconst_null
      29: areturn

  public it.unimi.dsi.fastutil.objects.ObjectArrayList<net.minecraft.client.renderer.chunk.SectionRenderDispatcher$RenderSection> getVisibleSections();
    Code:
       0: aload_0
       1: getfield      #63                 // Field visibleSections:Lit/unimi/dsi/fastutil/objects/ObjectArrayList;
       4: areturn

  public net.minecraft.client.renderer.SectionOcclusionGraph getSectionOcclusionGraph();
    Code:
       0: aload_0
       1: getfield      #54                 // Field sectionOcclusionGraph:Lnet/minecraft/client/renderer/SectionOcclusionGraph;
       4: areturn

  public net.minecraft.client.renderer.culling.Frustum getCapturedFrustum();
    Code:
       0: aload_0
       1: getfield      #577                // Field capturedFrustum:Lnet/minecraft/client/renderer/culling/Frustum;
       4: areturn

  public net.minecraft.client.renderer.CloudRenderer getCloudRenderer();
    Code:
       0: aload_0
       1: getfield      #10                 // Field cloudRenderer:Lnet/minecraft/client/renderer/CloudRenderer;
       4: areturn

  public int getTicks();
    Code:
       0: aload_0
       1: getfield      #768                // Field ticks:I
       4: ireturn

  public void iterateVisibleBlockEntities(java.util.function.Consumer<net.minecraft.world.level.block.entity.BlockEntity>);
    Code:
       0: aload_0
       1: getfield      #63                 // Field visibleSections:Lit/unimi/dsi/fastutil/objects/ObjectArrayList;
       4: invokevirtual #480                // Method it/unimi/dsi/fastutil/objects/ObjectArrayList.iterator:()Lit/unimi/dsi/fastutil/objects/ObjectListIterator;
       7: astore_2
       8: aload_2
       9: invokeinterface #484,  1          // InterfaceMethod java/util/Iterator.hasNext:()Z
      14: ifeq          45
      17: aload_2
      18: invokeinterface #489,  1          // InterfaceMethod java/util/Iterator.next:()Ljava/lang/Object;
      23: checkcast     #492                // class net/minecraft/client/renderer/chunk/SectionRenderDispatcher$RenderSection
      26: astore_3
      27: aload_3
      28: invokevirtual #494                // Method net/minecraft/client/renderer/chunk/SectionRenderDispatcher$RenderSection.getSectionMesh:()Lnet/minecraft/client/renderer/chunk/SectionMesh;
      31: invokeinterface #1234,  1         // InterfaceMethod net/minecraft/client/renderer/chunk/SectionMesh.getRenderableBlockEntities:()Ljava/util/List;
      36: aload_1
      37: invokeinterface #2002,  2         // InterfaceMethod java/util/List.forEach:(Ljava/util/function/Consumer;)V
      42: goto          8
      45: aload_0
      46: getfield      #317                // Field level:Lnet/minecraft/client/multiplayer/ClientLevel;
      49: invokevirtual #1302               // Method net/minecraft/client/multiplayer/ClientLevel.getGloballyRenderedBlockEntities:()Ljava/util/Set;
      52: aload_1
      53: invokeinterface #2006,  2         // InterfaceMethod java/util/Set.forEach:(Ljava/util/function/Consumer;)V
      58: return

  public java.lang.Iterable<? extends net.neoforged.neoforge.client.IRenderableSection> getRenderableSections();
    Code:
       0: aload_0
       1: getfield      #63                 // Field visibleSections:Lit/unimi/dsi/fastutil/objects/ObjectArrayList;
       4: areturn

  public net.minecraft.gizmos.Gizmos$TemporaryCollection collectPerFrameGizmos();
    Code:
       0: aload_0
       1: getfield      #130                // Field collectedGizmos:Lnet/minecraft/gizmos/SimpleGizmoCollector;
       4: invokestatic  #2007               // Method net/minecraft/gizmos/Gizmos.withCollector:(Lnet/minecraft/gizmos/GizmoCollector;)Lnet/minecraft/gizmos/Gizmos$TemporaryCollection;
       7: areturn

  static {};
    Code:
       0: ldc_w         #2444               // String transparency
       3: invokestatic  #2446               // Method net/minecraft/resources/Identifier.withDefaultNamespace:(Ljava/lang/String;)Lnet/minecraft/resources/Identifier;
       6: putstatic     #250                // Field TRANSPARENCY_POST_CHAIN_ID:Lnet/minecraft/resources/Identifier;
       9: ldc_w         #924                // String entity_outline
      12: invokestatic  #2446               // Method net/minecraft/resources/Identifier.withDefaultNamespace:(Ljava/lang/String;)Lnet/minecraft/resources/Identifier;
      15: putstatic     #970                // Field ENTITY_OUTLINE_POST_CHAIN_ID:Lnet/minecraft/resources/Identifier;
      18: return
}
